[{"country":"Algeria","location":{"lat":36.762,"lng":4.3163}},{"country":"Morocco","location":{"lat":32.2878,"lng":-6.4328}},{"country":"Iran","location":{"lat":32.6267,"lng":51.4392}},{"country":"Romania","location":{"lat":45.6667,"lng":24.2611}},{"country":"Brazil","location":{"lat":-17.0719,"lng":-41.5239}},{"country":"China","location":{"lat":39.5054,"lng":116.5642}},{"country":"Sweden","location":{"lat":58.705,"lng":13.828}},{"country":"United States","location":{"lat":43.7296,"lng":-98.0337}},{"country":"Czechia","location":{"lat":48.917,"lng":17.09}},{"country":"Thailand","location":{"lat":16.9364,"lng":104.7103}},{"country":"Philippines","location":{"lat":9.3667,"lng":122.8}},{"country":"Italy","location":{"lat":45.5781,"lng":8.9183}},{"country":"Chile","location":{"lat":-33.5333,"lng":-70.7167}},{"country":"Ukraine","location":{"lat":48.5167,"lng":25.0333}},{"country":"United States","location":{"lat":40.946,"lng":-72.8811}},{"country":"Finland","location":{"lat":60.7884,"lng":25.0247}},{"country":"United States","location":{"lat":33.0874,"lng":-83.2414}},{"country":"Germany","location":{"lat":52.25,"lng":10.2167}},{"country":"Brazil","location":{"lat":-21.7939,"lng":-48.1758}},{"country":"India","location":{"lat":19.95,"lng":79.3}},{"country":"Philippines","location":{"lat":16.6667,"lng":120.4}},{"country":"Mexico","location":{"lat":19.7125,"lng":-99.9511}},{"country":"Mexico","location":{"lat":16.3514,"lng":-94.4836}},{"country":"Syria","location":{"lat":32.7356,"lng":36.0669}},{"country":"United States","location":{"lat":40.9047,"lng":-74.4048}},{"country":"China","location":{"lat":36.5726,"lng":111.7176}},{"country":"France","location":{"lat":47.3017,"lng":5.1356}},{"country":"Italy","location":{"lat":41.5,"lng":13.0667}},{"country":"United Kingdom","location":{"lat":51.7109,"lng":-0.0825}},{"country":"United States","location":{"lat":40.1416,"lng":-79.5999}},{"country":"Ukraine","location":{"lat":47.3855,"lng":34.9879}},{"country":"Belarus","location":{"lat":54.2479,"lng":29.7966}},{"country":"United States","location":{"lat":44.2752,"lng":-105.4983}},{"country":"China","location":{"lat":23.1863,"lng":116.4728}},{"country":"Japan","location":{"lat":32.9297,"lng":130.4528}},{"country":"Russia","location":{"lat":53.85,"lng":46.35}},{"country":"Philippines","location":{"lat":6.55,"lng":125.4667}},{"country":"United States","location":{"lat":33.0249,"lng":-109.2883}},{"country":"United States","location":{"lat":40.0249,"lng":-77.546}},{"country":"Italy","location":{"lat":44.9,"lng":9.6}},{"country":"United Kingdom","location":{"lat":55.8908,"lng":-4.1522}},{"country":"United States","location":{"lat":30.061,"lng":-90.6928}},{"country":"Philippines","location":{"lat":13.2589,"lng":123.4953}},{"country":"Mexico","location":{"lat":18.5167,"lng":-95.7833}},{"country":"Iran","location":{"lat":27.665,"lng":54.1369}},{"country":"Ghana","location":{"lat":6.6114,"lng":0.4703}},{"country":"Germany","location":{"lat":47.865,"lng":12.0097}},{"country":"Philippines","location":{"lat":6.55,"lng":124.6667}},{"country":"Brazil","location":{"lat":-12.7058,"lng":-44.0069}},{"country":"Nepal","location":{"lat":26.4833,"lng":87.2833}},{"country":"Indonesia","location":{"lat":-6.9667,"lng":110.4167}},{"country":"Sudan","location":{"lat":18.4833,"lng":31.8167}},{"country":"Norway","location":{"lat":61.1844,"lng":7.2422}},{"country":"Colombia","location":{"lat":4.4908,"lng":-74.2594}},{"country":"Australia","location":{"lat":-14.4667,"lng":132.2667}},{"country":"Mexico","location":{"lat":21.2964,"lng":-88.2706}},{"country":"Egypt","location":{"lat":25.7333,"lng":32.7125}},{"country":"Hungary","location":{"lat":48.3941,"lng":21.6561}},{"country":"France","location":{"lat":46.1344,"lng":3.4564}},{"country":"France","location":{"lat":49.2231,"lng":5.9928}},{"country":"Switzerland","location":{"lat":47.5236,"lng":7.5697}},{"country":"Germany","location":{"lat":48.8,"lng":9.5333}},{"country":"United States","location":{"lat":40.4311,"lng":-78.393}},{"country":"United States","location":{"lat":38.6229,"lng":-122.8651}},{"country":"France","location":{"lat":43.89,"lng":-0.5}},{"country":"Italy","location":{"lat":45.15,"lng":9.1333}},{"country":"Mexico","location":{"lat":19.3083,"lng":-100.1422}},{"country":"United States","location":{"lat":33.9379,"lng":-118.1312}},{"country":"Bolivia","location":{"lat":-21.5317,"lng":-64.7311}},{"country":"Hungary","location":{"lat":47.7753,"lng":19.1311}},{"country":"Japan","location":{"lat":35.3086,"lng":138.935}},{"country":"United Kingdom","location":{"lat":52.9519,"lng":-1.4856}},{"country":"Ecuador","location":{"lat":-2.7333,"lng":-78.8333}},{"country":"Italy","location":{"lat":40.9667,"lng":14.2333}},{"country":"Brazil","location":{"lat":-14.0208,"lng":-41.2478}},{"country":"France","location":{"lat":50.4581,"lng":2.9472}},{"country":"United States","location":{"lat":41.1918,"lng":-73.1953}},{"country":"Morocco","location":{"lat":33.7333,"lng":-7.2}},{"country":"Chad","location":{"lat":13.4586,"lng":14.7147}},{"country":"United States","location":{"lat":41.3069,"lng":-72.4665}},{"country":"Russia","location":{"lat":56.5833,"lng":104.1167}},{"country":"United States","location":{"lat":35.1927,"lng":-79.404}},{"country":"Serbia","location":{"lat":43.3192,"lng":21.8961}},{"country":"Brazil","location":{"lat":-22.8858,"lng":-48.445}},{"country":"Japan","location":{"lat":36,"lng":139.6239}},{"country":"Nigeria","location":{"lat":4.95,"lng":8.325}},{"country":"United States","location":{"lat":44.0538,"lng":-122.981}},{"country":"Germany","location":{"lat":48.7508,"lng":8.8706}},{"country":"Germany","location":{"lat":48.6928,"lng":9.1428}},{"country":"Australia","location":{"lat":-20.4017,"lng":148.5814}},{"country":"United States","location":{"lat":42.9037,"lng":-73.6895}},{"country":"United Kingdom","location":{"lat":53.725,"lng":-1.863}},{"country":"Brazil","location":{"lat":-3.6058,"lng":-55.3319}},{"country":"United States","location":{"lat":37.5689,"lng":-85.2578}},{"country":"Italy","location":{"lat":45.2848,"lng":9.1407}},{"country":"United Kingdom","location":{"lat":51.791,"lng":-2.6162}},{"country":"United Kingdom","location":{"lat":50.25,"lng":-5.268}},{"country":"Germany","location":{"lat":51.1333,"lng":9.55}},{"country":"South Africa","location":{"lat":-28.4572,"lng":21.2425}},{"country":"Macedonia","location":{"lat":41.4839,"lng":22.0892}}]