[{"country":"Germany","location":{"lat":50.3,"lng":8.2667}},{"country":"United Kingdom","location":{"lat":55.81,"lng":-3.9333}},{"country":"France","location":{"lat":47.0581,"lng":6.6061}},{"country":"United Kingdom","location":{"lat":51.9302,"lng":-2.4048}},{"country":"Hungary","location":{"lat":47.2167,"lng":20.7667}},{"country":"Bolivia","location":{"lat":-18.9633,"lng":-57.7978}},{"country":"Czechia","location":{"lat":49.9019,"lng":16.4473}},{"country":"Ukraine","location":{"lat":47.2039,"lng":30.9125}},{"country":"India","location":{"lat":16.7333,"lng":77.9833}},{"country":"Georgia","location":{"lat":41.9975,"lng":43.5986}},{"country":"United States","location":{"lat":43.2469,"lng":-73.6659}},{"country":"Uruguay","location":{"lat":-31.1833,"lng":-55.7667}},{"country":"Philippines","location":{"lat":16.1869,"lng":119.8592}},{"country":"United States","location":{"lat":40.4583,"lng":-78.4768}},{"country":"Thailand","location":{"lat":16.4333,"lng":103.5}},{"country":"United States","location":{"lat":41.2483,"lng":-80.7444}},{"country":"United Kingdom","location":{"lat":52.604,"lng":-1.154}},{"country":"United States","location":{"lat":38.9955,"lng":-77.3693}},{"country":"Brazil","location":{"lat":-28.4669,"lng":-49.0069}},{"country":"Czechia","location":{"lat":50.0358,"lng":16.4988}},{"country":"Brazil","location":{"lat":-17.5269,"lng":-43.0158}},{"country":"United States","location":{"lat":36.9607,"lng":-121.8807}},{"country":"Romania","location":{"lat":45.6175,"lng":25.6878}},{"country":"Cameroon","location":{"lat":5.7167,"lng":10.9167}},{"country":"Côte D’Ivoire","location":{"lat":7.0123,"lng":-7.4864}},{"country":"United Kingdom","location":{"lat":52.6835,"lng":-1.8265}},{"country":"Portugal","location":{"lat":41.0833,"lng":-7.1333}},{"country":"Italy","location":{"lat":45.6649,"lng":8.7914}},{"country":"China","location":{"lat":41.7277,"lng":82.9364}},{"country":"France","location":{"lat":45.8186,"lng":4.6631}},{"country":"United Kingdom","location":{"lat":51.3162,"lng":-0.561}},{"country":"France","location":{"lat":47.7633,"lng":-3.2389}},{"country":"Greenland","location":{"lat":73.369,"lng":-56.0598}},{"country":"Philippines","location":{"lat":11.45,"lng":124.4167}},{"country":"France","location":{"lat":49.5092,"lng":-1.4692}},{"country":"Brazil","location":{"lat":-23.9639,"lng":-47.5069}},{"country":"Morocco","location":{"lat":34.26,"lng":-5.93}},{"country":"Chile","location":{"lat":-33.9,"lng":-71.4667}},{"country":"Venezuela","location":{"lat":8.9219,"lng":-67.4283}},{"country":"Philippines","location":{"lat":11.05,"lng":122.6667}},{"country":"Italy","location":{"lat":39.3211,"lng":8.6531}},{"country":"Morocco","location":{"lat":34.2894,"lng":-4.9481}},{"country":"United States","location":{"lat":42.1152,"lng":-88.1019}},{"country":"Philippines","location":{"lat":10.35,"lng":124.9667}},{"country":"India","location":{"lat":16.87,"lng":81.93}},{"country":"United Kingdom","location":{"lat":51.898,"lng":0.198}},{"country":"Brazil","location":{"lat":-25.8558,"lng":-52.5228}},{"country":"France","location":{"lat":46.3092,"lng":4.7844}},{"country":"Armenia","location":{"lat":39.5208,"lng":46.0322}},{"country":"Brazil","location":{"lat":-26.4842,"lng":-51.9906}},{"country":"Germany","location":{"lat":50.9053,"lng":7.5422}},{"country":"Russia","location":{"lat":55.3167,"lng":89.8167}},{"country":"Germany","location":{"lat":49.3494,"lng":7.2594}},{"country":"Korea, South","location":{"lat":34.7936,"lng":126.3886}},{"country":"Iran","location":{"lat":32.6153,"lng":51.5556}},{"country":"Madagascar","location":{"lat":-21.4329,"lng":44.3333}},{"country":"Italy","location":{"lat":40.4667,"lng":17.7333}},{"country":"Philippines","location":{"lat":7.0178,"lng":124.4974}},{"country":"Brazil","location":{"lat":-16.685,"lng":-44.365}},{"country":"Hungary","location":{"lat":47.3817,"lng":16.5519}},{"country":"Oman","location":{"lat":19.9333,"lng":56.3167}},{"country":"Yemen","location":{"lat":13.6957,"lng":44.7314}},{"country":"Russia","location":{"lat":58.75,"lng":42.7}},{"country":"Russia","location":{"lat":42.5658,"lng":47.5631}},{"country":"China","location":{"lat":50.2458,"lng":127.4886}},{"country":"France","location":{"lat":45.5494,"lng":3.7417}},{"country":"Tunisia","location":{"lat":37.215,"lng":10.12}},{"country":"Spain","location":{"lat":41.5756,"lng":1.6092}},{"country":"Philippines","location":{"lat":13.0333,"lng":124.1833}},{"country":"Spain","location":{"lat":42.7833,"lng":-4.8333}},{"country":"Romania","location":{"lat":47.153,"lng":27.6619}},{"country":"Philippines","location":{"lat":18.2519,"lng":120.6107}},{"country":"Morocco","location":{"lat":34.4314,"lng":-4.9642}},{"country":"Egypt","location":{"lat":28.9831,"lng":30.8492}},{"country":"Algeria","location":{"lat":36.4311,"lng":5.36}},{"country":"United States","location":{"lat":40.15,"lng":-82.6881}},{"country":"Brazil","location":{"lat":-21.275,"lng":-43.1789}},{"country":"Philippines","location":{"lat":15.4833,"lng":120.9667}},{"country":"Mexico","location":{"lat":19.3133,"lng":-97.9228}},{"country":"France","location":{"lat":45.8336,"lng":6.1639}},{"country":"Hungary","location":{"lat":47.6067,"lng":19.5967}},{"country":"United States","location":{"lat":42.3759,"lng":-71.1185}},{"country":"Iraq","location":{"lat":31.8416,"lng":47.1512}},{"country":"Germany","location":{"lat":50.3381,"lng":7.7106}},{"country":"South Sudan","location":{"lat":4.9151,"lng":29.4769}},{"country":"Austria","location":{"lat":48.0856,"lng":16.3131}},{"country":"Tanzania","location":{"lat":-7.9667,"lng":31.6167}},{"country":"Namibia","location":{"lat":-22.45,"lng":18.9667}},{"country":"Switzerland","location":{"lat":47.3081,"lng":8.5542}},{"country":"Brazil","location":{"lat":-17.5978,"lng":-44.7308}},{"country":"Spain","location":{"lat":41.6681,"lng":0.5561}},{"country":"Iran","location":{"lat":35.9975,"lng":45.8853}},{"country":"Japan","location":{"lat":33.7333,"lng":130.4667}},{"country":"France","location":{"lat":43.5151,"lng":4.9895}},{"country":"Brazil","location":{"lat":-4.3319,"lng":-40.1569}},{"country":"China","location":{"lat":23.0475,"lng":113.7493}},{"country":"Kuwait","location":{"lat":29.3375,"lng":47.6581}},{"country":"Thailand","location":{"lat":13.8369,"lng":100.3591}},{"country":"Canada","location":{"lat":45.4687,"lng":-73.6673}},{"country":"Colombia","location":{"lat":8.4353,"lng":-73.2864}}]