[{"country":"Brazil","location":{"lat":-11.2289,"lng":-41.9119}},{"country":"United States","location":{"lat":38.9654,"lng":-76.8773}},{"country":"United States","location":{"lat":47.7417,"lng":-122.6407}},{"country":"United States","location":{"lat":35.5706,"lng":-97.5567}},{"country":"Brazil","location":{"lat":-20.635,"lng":-40.75}},{"country":"United Kingdom","location":{"lat":51.1756,"lng":0.3955}},{"country":"Australia","location":{"lat":-20.0167,"lng":148.2333}},{"country":"Russia","location":{"lat":58.05,"lng":65.2667}},{"country":"Colombia","location":{"lat":7.4764,"lng":-73.9231}},{"country":"Germany","location":{"lat":48.7133,"lng":9.0028}},{"country":"Portugal","location":{"lat":38.65,"lng":-8.9833}},{"country":"United States","location":{"lat":38.4472,"lng":-90.3199}},{"country":"Israel","location":{"lat":32.0167,"lng":34.7667}},{"country":"Australia","location":{"lat":-33.074,"lng":151.451}},{"country":"France","location":{"lat":48.7717,"lng":5.1672}},{"country":"Portugal","location":{"lat":39.9167,"lng":-7.2333}},{"country":"Botswana","location":{"lat":-17.7983,"lng":25.1536}},{"country":"Austria","location":{"lat":48.5667,"lng":16.5667}},{"country":"China","location":{"lat":40.4202,"lng":114.0865}},{"country":"United States","location":{"lat":42.4786,"lng":-83.4893}},{"country":"United States","location":{"lat":28.658,"lng":-81.1872}},{"country":"Russia","location":{"lat":64.5167,"lng":34.7667}},{"country":"United States","location":{"lat":44.243,"lng":-74.2363}},{"country":"Brazil","location":{"lat":-12.53,"lng":-38.2989}},{"country":"Burundi","location":{"lat":-2.9,"lng":29.8167}},{"country":"United States","location":{"lat":27.8868,"lng":-81.8213}},{"country":"Peru","location":{"lat":-8.4143,"lng":-78.7524}},{"country":"Spain","location":{"lat":39.3611,"lng":-7.1333}},{"country":"United States","location":{"lat":37.8206,"lng":-85.9366}},{"country":"Mexico","location":{"lat":17.2,"lng":-100.4333}},{"country":"Japan","location":{"lat":35.7126,"lng":139.78}},{"country":"Israel","location":{"lat":32.0697,"lng":34.8117}},{"country":"Algeria","location":{"lat":36.7427,"lng":3.9019}},{"country":"Azerbaijan","location":{"lat":40.47,"lng":50.3247}},{"country":"Germany","location":{"lat":49.1469,"lng":8.22}},{"country":"Morocco","location":{"lat":32.0275,"lng":-3.0397}},{"country":"United States","location":{"lat":41.7282,"lng":-71.2629}},{"country":"Romania","location":{"lat":46.1,"lng":27.1797}},{"country":"Mexico","location":{"lat":28.4214,"lng":-100.7675}},{"country":"Afghanistan","location":{"lat":33.1757,"lng":68.7304}},{"country":"United Kingdom","location":{"lat":55.932,"lng":-4.494}},{"country":"United Kingdom","location":{"lat":52.6354,"lng":1.3431}},{"country":"Brazil","location":{"lat":-9.0122,"lng":-35.2225}},{"country":"Philippines","location":{"lat":8.1092,"lng":124.4392}},{"country":"Timor-Leste","location":{"lat":-8.5935,"lng":125.3273}},{"country":"Italy","location":{"lat":45.6167,"lng":9.25}},{"country":"Ukraine","location":{"lat":47.3878,"lng":30.1911}},{"country":"France","location":{"lat":47.9686,"lng":0.1606}},{"country":"Hungary","location":{"lat":48.0808,"lng":19.5194}},{"country":"Brazil","location":{"lat":-20.7619,"lng":-45.9178}},{"country":"Estonia","location":{"lat":59.2644,"lng":25.9628}},{"country":"China","location":{"lat":45.9313,"lng":83.6039}},{"country":"Egypt","location":{"lat":29.3005,"lng":31.1683}},{"country":"China","location":{"lat":38.0887,"lng":114.556}},{"country":"Brazil","location":{"lat":-16.6189,"lng":-42.1819}},{"country":"Netherlands","location":{"lat":52.0667,"lng":4.6333}},{"country":"Thailand","location":{"lat":14.3347,"lng":100.3037}},{"country":"Mexico","location":{"lat":18.6743,"lng":-97.0385}},{"country":"Uganda","location":{"lat":-0.8411,"lng":29.9419}},{"country":"United Kingdom","location":{"lat":53.6622,"lng":-1.6124}},{"country":"Poland","location":{"lat":51.5906,"lng":19.1328}},{"country":"Brazil","location":{"lat":-20.7939,"lng":-43.3439}},{"country":"Serbia","location":{"lat":43.8247,"lng":21.9519}},{"country":"Lithuania","location":{"lat":55.9979,"lng":22.9415}},{"country":"Argentina","location":{"lat":-41.6061,"lng":-65.3558}},{"country":"Mexico","location":{"lat":18.9,"lng":-98.45}},{"country":"United States","location":{"lat":40.3499,"lng":-104.9481}},{"country":"France","location":{"lat":49.2556,"lng":2.4383}},{"country":"United States","location":{"lat":40.1756,"lng":-80.191}},{"country":"Ukraine","location":{"lat":48.6044,"lng":38.0067}},{"country":"Argentina","location":{"lat":-34.6833,"lng":-58.55}},{"country":"Italy","location":{"lat":45.5333,"lng":9.1833}},{"country":"Brazil","location":{"lat":-20.8758,"lng":-45.5189}},{"country":"China","location":{"lat":21.6172,"lng":110.0319}},{"country":"United States","location":{"lat":19.5726,"lng":-155.958}},{"country":"Japan","location":{"lat":43.1683,"lng":143.2411}},{"country":"Argentina","location":{"lat":-34.5939,"lng":-60.9464}},{"country":"Spain","location":{"lat":36.7667,"lng":-6.35}},{"country":"United States","location":{"lat":27.7065,"lng":-82.4209}},{"country":"China","location":{"lat":34.35,"lng":108.7167}},{"country":"Argentina","location":{"lat":-40.5875,"lng":-67.7583}},{"country":"Armenia","location":{"lat":39.6833,"lng":45.4667}},{"country":"United States","location":{"lat":47.0966,"lng":-122.2111}},{"country":"United States","location":{"lat":44.5441,"lng":-69.6624}},{"country":"India","location":{"lat":13.9304,"lng":75.56}},{"country":"United States","location":{"lat":33.7777,"lng":-79.0111}},{"country":"France","location":{"lat":48.6428,"lng":2.2917}},{"country":"Philippines","location":{"lat":8.6,"lng":123.4667}},{"country":"Mexico","location":{"lat":16.3992,"lng":-95.6033}},{"country":"Congo (Kinshasa)","location":{"lat":-3.5968,"lng":26.6671}},{"country":"Russia","location":{"lat":53.8947,"lng":56.4686}},{"country":"Philippines","location":{"lat":9.5288,"lng":123.3064}},{"country":"China","location":{"lat":36.9218,"lng":109.9341}},{"country":"Italy","location":{"lat":40.3842,"lng":17.3547}},{"country":"Romania","location":{"lat":44.05,"lng":25.0833}},{"country":"United States","location":{"lat":42.4619,"lng":-83.0977}},{"country":"Germany","location":{"lat":48.6747,"lng":9.3817}},{"country":"Brazil","location":{"lat":-13.1039,"lng":-39.7958}},{"country":"Congo (Brazzaville)","location":{"lat":-2.9458,"lng":12.7147}},{"country":"Iran","location":{"lat":30.6667,"lng":51.5833}}]