[{"country": "Serbia", "code": "RS", "location": {"lat": 45.6109, "lng": 19.5274}}, {"country": "Estonia", "code": "EE", "location": {"lat": 58.8094, "lng": 25.4292}}, {"country": "Guatemala", "code": "GT", "location": {"lat": 14.9489, "lng": -89.7767}}, {"country": "Philippines", "code": "PH", "location": {"lat": 9.8694, "lng": 123.3959}}, {"country": "Russia", "code": "RU", "location": {"lat": 63.7415, "lng": 34.3222}}, {"country": "China", "code": "CN", "location": {"lat": 32.5293, "lng": 107.5658}}, {"country": "India", "code": "IN", "location": {"lat": 16.5833, "lng": 82.0167}}, {"country": "France", "code": "FR", "location": {"lat": 48.7114, "lng": 6.1631}}, {"country": "Colombia", "code": "CO", "location": {"lat": 6.7561, "lng": -73.1022}}, {"country": "Argentina", "code": "AR", "location": {"lat": -33.0442, "lng": -61.1681}}, {"country": "Brazil", "code": "BR", "location": {"lat": -3.7419, "lng": -43.36}}, {"country": "China", "code": "CN", "location": {"lat": 34.3422, "lng": 118.0097}}, {"country": "United Kingdom", "code": "GB", "location": {"lat": 51.449, "lng": -0.337}}, {"country": "Latvia", "code": "LV", "location": {"lat": 57.8667, "lng": 25.05}}, {"country": "France", "code": "FR", "location": {"lat": 44.9917, "lng": -0.2061}}, {"country": "Brazil", "code": "BR", "location": {"lat": -19.9778, "lng": -42.14}}, {"country": "France", "code": "FR", "location": {"lat": 48.4936, "lng": 3.5025}}, {"country": "Colombia", "code": "CO", "location": {"lat": 10.5911, "lng": -74.185}}, {"country": "United Kingdom", "code": "GB", "location": {"lat": 53.5402, "lng": -2.599}}, {"country": "Egypt", "code": "EG", "location": {"lat": 25.44, "lng": 30.55}}, {"country": "Mexico", "code": "MX", "location": {"lat": 19.0006, "lng": -98.8178}}, {"country": "China", "code": "CN", "location": {"lat": 30.6412, "lng": 116.5689}}, {"country": "Belgium", "code": "BE", "location": {"lat": 50.6, "lng": 5.35}}, {"country": "Italy", "code": "IT", "location": {"lat": 44.8667, "lng": 10.0667}}, {"country": "India", "code": "IN", "location": {"lat": 10.52, "lng": 76.21}}, {"country": "Portugal", "code": "PT", "location": {"lat": 41.5667, "lng": -8.2667}}, {"country": "Romania", "code": "RO", "location": {"lat": 45.2333, "lng": 25.9392}}, {"country": "United States", "code": "US", "location": {"lat": 43.0427, "lng": -85.6016}}, {"country": "United States", "code": "US", "location": {"lat": 34.4382, "lng": -119.6286}}, {"country": "United States", "code": "US", "location": {"lat": 48.4202, "lng": -122.3115}}, {"country": "United States", "code": "US", "location": {"lat": 38.7153, "lng": -121.361}}, {"country": "Ukraine", "code": "UA", "location": {"lat": 47.7225, "lng": 29.96}}, {"country": "Spain", "code": "ES", "location": {"lat": 38.4789, "lng": -0.7967}}, {"country": "Korea, South", "code": "KR", "location": {"lat": 37.2939, "lng": 127.6383}}, {"country": "United States", "code": "US", "location": {"lat": 35.0253, "lng": -110.7098}}, {"country": "United Kingdom", "code": "GB", "location": {"lat": 51.615, "lng": -2.959}}, {"country": "Canada", "code": "CA", "location": {"lat": 49.6869, "lng": -83.6544}}, {"country": "Hungary", "code": "HU", "location": {"lat": 47.9228, "lng": 21.0519}}, {"country": "China", "code": "CN", "location": {"lat": 33.2033, "lng": 106.9544}}, {"country": "Philippines", "code": "PH", "location": {"lat": 13.3167, "lng": 122.0833}}, {"country": "Canada", "code": "CA", "location": {"lat": 43.73, "lng": -80.95}}, {"country": "Germany", "code": "DE", "location": {"lat": 49.9422, "lng": 11.7203}}, {"country": "Japan", "code": "JP", "location": {"lat": 34.4089, "lng": 133.205}}, {"country": "Japan", "code": "JP", "location": {"lat": 35.7225, "lng": 140.0997}}, {"country": "Belgium", "code": "BE", "location": {"lat": 50.0294, "lng": 4.1667}}, {"country": "Brazil", "code": "BR", "location": {"lat": -14.525, "lng": -49.1408}}, {"country": "Pakistan", "code": "PK", "location": {"lat": 32.9889, "lng": 70.6056}}, {"country": "Germany", "code": "DE", "location": {"lat": 48.1747, "lng": 8.0717}}, {"country": "Brazil", "code": "BR", "location": {"lat": -1.5228, "lng": -52.5819}}, {"country": "United States", "code": "US", "location": {"lat": 43.6954, "lng": -70.3539}}, {"country": "United States", "code": "US", "location": {"lat": 40.7637, "lng": -73.5245}}, {"country": "Brazil", "code": "BR", "location": {"lat": -14.0928, "lng": -46.3689}}, {"country": "Mexico", "code": "MX", "location": {"lat": 16.7367, "lng": -92.6383}}, {"country": "Hungary", "code": "HU", "location": {"lat": 47.8167, "lng": 21.5}}, {"country": "Brazil", "code": "BR", "location": {"lat": -9.5019, "lng": -36.0228}}, {"country": "Russia", "code": "RU", "location": {"lat": 43.1875, "lng": 44.9019}}, {"country": "Bosnia And Herzegovina", "code": "BA", "location": {"lat": 44.7667, "lng": 16.6667}}, {"country": "United Kingdom", "code": "GB", "location": {"lat": 52.5983, "lng": -2.168}}, {"country": "Germany", "code": "DE", "location": {"lat": 51.805, "lng": 10.3356}}, {"country": "United States", "code": "US", "location": {"lat": 45.5471, "lng": -122.4391}}, {"country": "United States", "code": "US", "location": {"lat": 38.0725, "lng": -122.1525}}, {"country": "Iran", "code": "IR", "location": {"lat": 32.8019, "lng": 51.6636}}, {"country": "Guinea-Bissau", "code": "GW", "location": {"lat": 11.8592, "lng": -15.5956}}, {"country": "Zambia", "code": "ZM", "location": {"lat": -15.8667, "lng": 27.7667}}, {"country": "China", "code": "CN", "location": {"lat": 35.7261, "lng": 111.7108}}, {"country": "United States", "code": "US", "location": {"lat": 37.9806, "lng": -85.6999}}, {"country": "Italy", "code": "IT", "location": {"lat": 46, "lng": 13.3}}, {"country": "Albania", "code": "AL", "location": {"lat": 40.6841, "lng": 19.6194}}, {"country": "Portugal", "code": "PT", "location": {"lat": 38.65, "lng": -8.9833}}, {"country": "Germany", "code": "DE", "location": {"lat": 51.1275, "lng": 14.1797}}, {"country": "Brazil", "code": "BR", "location": {"lat": -21.2364, "lng": -47.9733}}, {"country": "Honduras", "code": "HN", "location": {"lat": 15.6667, "lng": -87.0333}}, {"country": "United States", "code": "US", "location": {"lat": 36.8432, "lng": -83.3184}}, {"country": "Czechia", "code": "CZ", "location": {"lat": 50.0833, "lng": 14.4167}}, {"country": "Germany", "code": "DE", "location": {"lat": 53.1667, "lng": 8.6167}}, {"country": "United States", "code": "US", "location": {"lat": 40.1235, "lng": -76.0332}}, {"country": "Germany", "code": "DE", "location": {"lat": 47.7208, "lng": 9.3917}}, {"country": "Canada", "code": "CA", "location": {"lat": 43.15, "lng": -80.95}}, {"country": "Colombia", "code": "CO", "location": {"lat": 4.4136, "lng": -76.1547}}, {"country": "Russia", "code": "RU", "location": {"lat": 52.1167, "lng": 47.2}}, {"country": "Somalia", "code": "SO", "location": {"lat": 2.7833, "lng": 45.5}}, {"country": "United States", "code": "US", "location": {"lat": 33.6909, "lng": -117.1849}}, {"country": "Finland", "code": "FI", "location": {"lat": 61.3556, "lng": 22.9402}}, {"country": "Spain", "code": "ES", "location": {"lat": 37.9, "lng": -3.1167}}, {"country": "Switzerland", "code": "CH", "location": {"lat": 46.9433, "lng": 7.7853}}, {"country": "United States", "code": "US", "location": {"lat": 40.906, "lng": -73.1278}}, {"country": "Russia", "code": "RU", "location": {"lat": 67.4667, "lng": 86.5667}}, {"country": "Madagascar", "code": "MG", "location": {"lat": -19.5162, "lng": 45.4666}}, {"country": "United States", "code": "US", "location": {"lat": 45.8323, "lng": -119.2858}}, {"country": "Moldova", "code": "MD", "location": {"lat": 46.8614, "lng": 29.4692}}, {"country": "Serbia", "code": "RS", "location": {"lat": 44.4167, "lng": 21.9333}}, {"country": "Colombia", "code": "CO", "location": {"lat": 10.8858, "lng": -72.8481}}, {"country": "Germany", "code": "DE", "location": {"lat": 51.4667, "lng": 12.2036}}, {"country": "France", "code": "FR", "location": {"lat": 49.5406, "lng": 5.7794}}, {"country": "Oman", "code": "OM", "location": {"lat": 19.9333, "lng": 56.3167}}, {"country": "United States", "code": "US", "location": {"lat": 41.2652, "lng": -75.8875}}, {"country": "Australia", "code": "AU", "location": {"lat": -38.15, "lng": 145.9333}}, {"country": "Finland", "code": "FI", "location": {"lat": 62.0292, "lng": 24.6236}}, {"country": "Brazil", "code": "BR", "location": {"lat": -19.5489, "lng": -42.12}}, {"country": "Italy", "code": "IT", "location": {"lat": 41.25, "lng": 14.0667}}]