[{"country":"Brazil","location":{"lat":-7.4019,"lng":-35.1158}},{"country":"Philippines","location":{"lat":16.6079,"lng":120.4378}},{"country":"United States","location":{"lat":33.3754,"lng":-86.8064}},{"country":"France","location":{"lat":49.0886,"lng":0.5983}},{"country":"Russia","location":{"lat":57.8036,"lng":60.0286}},{"country":"Gabon","location":{"lat":1.0171,"lng":13.9333}},{"country":"China","location":{"lat":40.6562,"lng":109.8345}},{"country":"United Kingdom","location":{"lat":52.6831,"lng":-1.92}},{"country":"United States","location":{"lat":40.0891,"lng":-85.6893}},{"country":"France","location":{"lat":50.4181,"lng":3.0181}},{"country":"Pakistan","location":{"lat":30.6706,"lng":73.1064}},{"country":"Canada","location":{"lat":45.6,"lng":-73.45}},{"country":"Italy","location":{"lat":40.8725,"lng":14.4369}},{"country":"Brazil","location":{"lat":-7.2669,"lng":-37.3508}},{"country":"United States","location":{"lat":41.4368,"lng":-97.3563}},{"country":"United Kingdom","location":{"lat":57.695,"lng":-4.258}},{"country":"United States","location":{"lat":39.2563,"lng":-74.727}},{"country":"Croatia","location":{"lat":42.6403,"lng":18.1083}},{"country":"United States","location":{"lat":43.9887,"lng":-121.3608}},{"country":"France","location":{"lat":42.6319,"lng":2.7564}},{"country":"Brazil","location":{"lat":-22.4039,"lng":-43.6628}},{"country":"United Kingdom","location":{"lat":51.702,"lng":-0.035}},{"country":"Brazil","location":{"lat":-29.1678,"lng":-51.1789}},{"country":"Russia","location":{"lat":56.0767,"lng":37.0622}},{"country":"Mexico","location":{"lat":19.8667,"lng":-103.15}},{"country":"United States","location":{"lat":40.9,"lng":-73.8064}},{"country":"United States","location":{"lat":40.6266,"lng":-75.3679}},{"country":"Germany","location":{"lat":51.2611,"lng":7.4667}},{"country":"France","location":{"lat":49.9425,"lng":4.6386}},{"country":"United States","location":{"lat":41.6637,"lng":-87.7959}},{"country":"Germany","location":{"lat":48.0608,"lng":12.2333}},{"country":"Russia","location":{"lat":55.3525,"lng":65.3281}},{"country":"Portugal","location":{"lat":40.7833,"lng":-7.0667}},{"country":"United States","location":{"lat":33.7634,"lng":-116.4271}},{"country":"Germany","location":{"lat":49.3536,"lng":11.1483}},{"country":"Finland","location":{"lat":62.9403,"lng":22.5167}},{"country":"United States","location":{"lat":48.4329,"lng":-114.3591}},{"country":"United States","location":{"lat":39.065,"lng":-77.4965}},{"country":"France","location":{"lat":43.3128,"lng":3.4186}},{"country":"Kosovo","location":{"lat":42.3667,"lng":21.1667}},{"country":"France","location":{"lat":43.1256,"lng":6.0108}},{"country":"China","location":{"lat":45.7564,"lng":130.5759}},{"country":"United States","location":{"lat":41.1666,"lng":-80.6963}},{"country":"United States","location":{"lat":39.3239,"lng":-94.924}},{"country":"Germany","location":{"lat":48.0425,"lng":7.8657}},{"country":"Brazil","location":{"lat":-28.6386,"lng":-53.6064}},{"country":"United States","location":{"lat":40.9107,"lng":-81.1189}},{"country":"Philippines","location":{"lat":17.5427,"lng":120.5203}},{"country":"Syria","location":{"lat":33.5722,"lng":36.4019}},{"country":"Austria","location":{"lat":48.4667,"lng":15.6833}},{"country":"Germany","location":{"lat":49.8431,"lng":8.1156}},{"country":"Indonesia","location":{"lat":-6.95,"lng":107.5667}},{"country":"Belgium","location":{"lat":51.2278,"lng":5.4422}},{"country":"United States","location":{"lat":40.4262,"lng":-79.7605}},{"country":"Argentina","location":{"lat":-37.6996,"lng":-63.1666}},{"country":"Germany","location":{"lat":48.1133,"lng":8.6061}},{"country":"Germany","location":{"lat":48.6214,"lng":9.0611}},{"country":"Brazil","location":{"lat":-22.5278,"lng":-45.495}},{"country":"United States","location":{"lat":44.5703,"lng":-88.092}},{"country":"France","location":{"lat":49.5064,"lng":0.0833}},{"country":"Argentina","location":{"lat":-26.5167,"lng":-61.1667}},{"country":"Mexico","location":{"lat":19.1667,"lng":-96.8666}},{"country":"Morocco","location":{"lat":32.6215,"lng":-8.7022}},{"country":"France","location":{"lat":49.1603,"lng":1.3358}},{"country":"Serbia","location":{"lat":44.0142,"lng":20.9394}},{"country":"Switzerland","location":{"lat":47.4164,"lng":8.05}},{"country":"United States","location":{"lat":36.8035,"lng":-114.1325}},{"country":"Colombia","location":{"lat":1.4933,"lng":-77.5214}},{"country":"United States","location":{"lat":39.325,"lng":-77.8666}},{"country":"United Kingdom","location":{"lat":51.3691,"lng":-0.365}},{"country":"Brazil","location":{"lat":-19.955,"lng":-44.7089}},{"country":"Montenegro","location":{"lat":42.2847,"lng":18.8453}},{"country":"India","location":{"lat":12.9,"lng":76.39}},{"country":"Canada","location":{"lat":42.7667,"lng":-80.9833}},{"country":"Korea, South","location":{"lat":37.3447,"lng":126.9683}},{"country":"Russia","location":{"lat":55.3333,"lng":86.0667}},{"country":"United States","location":{"lat":38.3221,"lng":-85.7673}},{"country":"France","location":{"lat":50.6728,"lng":2.895}},{"country":"Brazil","location":{"lat":-12.6908,"lng":-43.1839}},{"country":"Italy","location":{"lat":42.3347,"lng":12.3003}},{"country":"Mexico","location":{"lat":20.1144,"lng":-98.8867}},{"country":"Spain","location":{"lat":41.1433,"lng":1.3769}},{"country":"Japan","location":{"lat":38.9144,"lng":139.8364}},{"country":"Italy","location":{"lat":43.6766,"lng":12.645}},{"country":"Brazil","location":{"lat":-23.415,"lng":-46.035}},{"country":"United States","location":{"lat":42.2121,"lng":-70.7652}},{"country":"United States","location":{"lat":27.4702,"lng":-82.5552}},{"country":"El Salvador","location":{"lat":13.6333,"lng":-88.8}},{"country":"Russia","location":{"lat":61.5167,"lng":30.2}},{"country":"India","location":{"lat":28.8418,"lng":78.7568}},{"country":"China","location":{"lat":37.1012,"lng":79.9327}},{"country":"Ukraine","location":{"lat":48.1144,"lng":38.1606}},{"country":"Philippines","location":{"lat":13.3667,"lng":122.65}},{"country":"Germany","location":{"lat":50.8933,"lng":13.6667}},{"country":"Italy","location":{"lat":45.8667,"lng":11.5167}},{"country":"India","location":{"lat":27.6119,"lng":75.1397}},{"country":"Germany","location":{"lat":53.5881,"lng":6.6697}},{"country":"United States","location":{"lat":35.1775,"lng":-118.646}},{"country":"Paraguay","location":{"lat":-25.05,"lng":-57.09}},{"country":"Brazil","location":{"lat":-9.3967,"lng":-36.1536}}]