[{"country": "Argentina", "code": "AR", "location": {"lat": -34.5, "lng": -58.7}}, {"country": "United States", "code": "US", "location": {"lat": 44.8228, "lng": -87.366}}, {"country": "Australia", "code": "AU", "location": {"lat": -33.2833, "lng": 149.1}}, {"country": "Yemen", "code": "YE", "location": {"lat": 14.704, "lng": 43.599}}, {"country": "Italy", "code": "IT", "location": {"lat": 44.8873, "lng": 11.066}}, {"country": "Madagascar", "code": "MG", "location": {"lat": -13.375, "lng": 50.01}}, {"country": "Egypt", "code": "EG", "location": {"lat": 28.3597, "lng": 33.0775}}, {"country": "Congo (Kinshasa)", "code": "CD", "location": {"lat": -5.95, "lng": 28.0167}}, {"country": "Germany", "code": "DE", "location": {"lat": 47.795, "lng": 11.0603}}, {"country": "United States", "code": "US", "location": {"lat": 40.6154, "lng": -75.5503}}, {"country": "United States", "code": "US", "location": {"lat": 43.335, "lng": -73.6824}}, {"country": "Benin", "code": "BJ", "location": {"lat": 6.8167, "lng": 1.7833}}, {"country": "Italy", "code": "IT", "location": {"lat": 45.2, "lng": 7.7833}}, {"country": "France", "code": "FR", "location": {"lat": 49.5811, "lng": 2.9989}}, {"country": "United States", "code": "US", "location": {"lat": 40.1008, "lng": -76.09}}, {"country": "Netherlands", "code": "NL", "location": {"lat": 52.0672, "lng": 5.1969}}, {"country": "Greece", "code": "GR", "location": {"lat": 40.935, "lng": 24.415}}, {"country": "Iraq", "code": "IQ", "location": {"lat": 36.3964, "lng": 44.3436}}, {"country": "United States", "code": "US", "location": {"lat": 41.0695, "lng": -80.058}}, {"country": "Slovenia", "code": "SI", "location": {"lat": 46.4839, "lng": 13.7894}}, {"country": "France", "code": "FR", "location": {"lat": 45.5906, "lng": 4.7689}}, {"country": "Morocco", "code": "MA", "location": {"lat": 35.1069, "lng": -3.0656}}, {"country": "Morocco", "code": "MA", "location": {"lat": 35.1536, "lng": -2.9861}}, {"country": "Slovenia", "code": "SI", "location": {"lat": 46.3456, "lng": 14.835}}, {"country": "Russia", "code": "RU", "location": {"lat": 43.2036, "lng": 46.1322}}, {"country": "Guatemala", "code": "GT", "location": {"lat": 14.4741, "lng": -90.6247}}, {"country": "Latvia", "code": "LV", "location": {"lat": 56.42, "lng": 24.0097}}, {"country": "Philippines", "code": "PH", "location": {"lat": 14.5167, "lng": 121.2667}}, {"country": "Brazil", "code": "BR", "location": {"lat": -11.55, "lng": -41.1558}}, {"country": "Venezuela", "code": "VE", "location": {"lat": 10.1692, "lng": -70.0783}}, {"country": "Poland", "code": "PL", "location": {"lat": 51.9397, "lng": 15.505}}, {"country": "Italy", "code": "IT", "location": {"lat": 41.8167, "lng": 12.8}}, {"country": "United States", "code": "US", "location": {"lat": 47.871, "lng": -121.8043}}, {"country": "Brazil", "code": "BR", "location": {"lat": -27.6208, "lng": -52.38}}, {"country": "Philippines", "code": "PH", "location": {"lat": 10.8833, "lng": 122.4833}}, {"country": "Brazil", "code": "BR", "location": {"lat": -20.735, "lng": -49.5839}}, {"country": "Russia", "code": "RU", "location": {"lat": 53.8419, "lng": 57.4611}}, {"country": "Brazil", "code": "BR", "location": {"lat": -7.2508, "lng": -42.5428}}, {"country": "India", "code": "IN", "location": {"lat": 23.03, "lng": 72.58}}, {"country": "United States", "code": "US", "location": {"lat": 42.132, "lng": -83.2374}}, {"country": "Philippines", "code": "PH", "location": {"lat": 12.6714, "lng": 123.875}}, {"country": "United States", "code": "US", "location": {"lat": 41.3099, "lng": -105.6085}}, {"country": "United States", "code": "US", "location": {"lat": 40.5321, "lng": -74.5415}}, {"country": "United States", "code": "US", "location": {"lat": 45.5613, "lng": -122.8369}}, {"country": "China", "code": "CN", "location": {"lat": 24.0668, "lng": 116.4547}}, {"country": "Myanmar", "code": "MM", "location": {"lat": 16.7547, "lng": 96.5193}}, {"country": "Italy", "code": "IT", "location": {"lat": 43.1667, "lng": 11.7667}}, {"country": "United States", "code": "US", "location": {"lat": 45.0657, "lng": -93.015}}, {"country": "United States", "code": "US", "location": {"lat": 39.4067, "lng": -76.4781}}, {"country": "Burkina Faso", "code": "BF", "location": {"lat": 11.5478, "lng": -1.775}}, {"country": "Russia", "code": "RU", "location": {"lat": 53.1142, "lng": 45.0601}}, {"country": "Congo (Kinshasa)", "code": "CD", "location": {"lat": 4.1904, "lng": 19.88}}, {"country": "United States", "code": "US", "location": {"lat": 40.8463, "lng": -74.0388}}, {"country": "United States", "code": "US", "location": {"lat": 43.0157, "lng": -70.9006}}, {"country": "Canada", "code": "CA", "location": {"lat": 47.8333, "lng": -69.5333}}, {"country": "United States", "code": "US", "location": {"lat": 41.2649, "lng": -73.3}}, {"country": "China", "code": "CN", "location": {"lat": 42.5279, "lng": 125.678}}, {"country": "United Kingdom", "code": "GB", "location": {"lat": 51.6185, "lng": -0.2729}}, {"country": "Greece", "code": "GR", "location": {"lat": 40.9833, "lng": 24.7}}, {"country": "United States", "code": "US", "location": {"lat": 25.9433, "lng": -80.2426}}, {"country": "United States", "code": "US", "location": {"lat": 40.3445, "lng": -76.795}}, {"country": "Ukraine", "code": "UA", "location": {"lat": 46.8333, "lng": 33.4167}}, {"country": "Italy", "code": "IT", "location": {"lat": 37.7127, "lng": 12.4996}}, {"country": "Japan", "code": "JP", "location": {"lat": 35.25, "lng": 136.7833}}, {"country": "France", "code": "FR", "location": {"lat": 49.2756, "lng": 2.4683}}, {"country": "Russia", "code": "RU", "location": {"lat": 65.9998, "lng": 57.5414}}, {"country": "Hungary", "code": "HU", "location": {"lat": 47.3553, "lng": 19.0844}}, {"country": "China", "code": "CN", "location": {"lat": 42.0608, "lng": 86.5686}}, {"country": "Spain", "code": "ES", "location": {"lat": 37.65, "lng": -5.5167}}, {"country": "United States", "code": "US", "location": {"lat": 40.0353, "lng": -83.1578}}, {"country": "Italy", "code": "IT", "location": {"lat": 40.7, "lng": 17.3333}}, {"country": "Nigeria", "code": "NG", "location": {"lat": 7.1104, "lng": 6.7399}}, {"country": "Thailand", "code": "TH", "location": {"lat": 7.0167, "lng": 100.4667}}, {"country": "New Zealand", "code": "NZ", "location": {"lat": -46.429, "lng": 168.362}}, {"country": "Pakistan", "code": "PK", "location": {"lat": 28.3006, "lng": 70.1302}}, {"country": "Italy", "code": "IT", "location": {"lat": 45.0833, "lng": 9.3}}, {"country": "Germany", "code": "DE", "location": {"lat": 48.45, "lng": 13.0833}}, {"country": "Philippines", "code": "PH", "location": {"lat": 6.8, "lng": 124.6333}}, {"country": "Kenya", "code": "KE", "location": {"lat": 0.0167, "lng": 37.0667}}, {"country": "United States", "code": "US", "location": {"lat": 42.8257, "lng": -78.249}}, {"country": "Peru", "code": "PE", "location": {"lat": -14.6939, "lng": -74.1241}}, {"country": "Germany", "code": "DE", "location": {"lat": 48.1667, "lng": 12.7167}}, {"country": "United States", "code": "US", "location": {"lat": 32.9068, "lng": -111.7624}}, {"country": "Colombia", "code": "CO", "location": {"lat": 6.2325, "lng": -75.1586}}, {"country": "Liberia", "code": "LR", "location": {"lat": 8.4167, "lng": -9.75}}, {"country": "Brazil", "code": "BR", "location": {"lat": -6.1108, "lng": -38.2089}}, {"country": "United States", "code": "US", "location": {"lat": 29.9284, "lng": -89.9179}}, {"country": "United Kingdom", "code": "GB", "location": {"lat": 50.8104, "lng": -0.4819}}, {"country": "Korea, South", "code": "KR", "location": {"lat": 35.2347, "lng": 128.3575}}, {"country": "Poland", "code": "PL", "location": {"lat": 54.5189, "lng": 18.5319}}, {"country": "France", "code": "FR", "location": {"lat": 48.9372, "lng": 2.1644}}, {"country": "United States", "code": "US", "location": {"lat": 34.0754, "lng": -80.9546}}, {"country": "Philippines", "code": "PH", "location": {"lat": 7.3821, "lng": 125.8017}}, {"country": "Poland", "code": "PL", "location": {"lat": 50.25, "lng": 19}}, {"country": "Australia", "code": "AU", "location": {"lat": -28.2564, "lng": 153.5781}}, {"country": "United States", "code": "US", "location": {"lat": 40.0772, "lng": -75.3035}}, {"country": "France", "code": "FR", "location": {"lat": 48.8742, "lng": 2.6381}}, {"country": "United States", "code": "US", "location": {"lat": 42.1764, "lng": -72.5719}}, {"country": "France", "code": "FR", "location": {"lat": 44.4081, "lng": 0.705}}, {"country": "Lithuania", "code": "LT", "location": {"lat": 54.9556, "lng": 23.0444}}]