[{"country": "Finland", "code": "FI", "location": {"lat": 60.8042, "lng": 23.4861}}, {"country": "Sri Lanka", "code": "LK", "location": {"lat": 9.4004, "lng": 80.3999}}, {"country": "United States", "code": "US", "location": {"lat": 40.809, "lng": -96.6788}}, {"country": "United States", "code": "US", "location": {"lat": 38.8518, "lng": -76.8708}}, {"country": "United States", "code": "US", "location": {"lat": 38.4361, "lng": -78.8735}}, {"country": "Liechtenstein", "code": "LI", "location": {"lat": 47.0667, "lng": 9.5025}}, {"country": "United Kingdom", "code": "GB", "location": {"lat": 51.5217, "lng": -0.7177}}, {"country": "United States", "code": "US", "location": {"lat": 32.5407, "lng": -86.2052}}, {"country": "United States", "code": "US", "location": {"lat": 36.393, "lng": -100.7976}}, {"country": "Mexico", "code": "MX", "location": {"lat": 16.4333, "lng": -95.0194}}, {"country": "United States", "code": "US", "location": {"lat": 41.4396, "lng": -96.4879}}, {"country": "Brazil", "code": "BR", "location": {"lat": -20.3919, "lng": -44.4878}}, {"country": "United States", "code": "US", "location": {"lat": 41.6594, "lng": -72.3905}}, {"country": "Italy", "code": "IT", "location": {"lat": 38, "lng": 13.65}}, {"country": "Turkey", "code": "TR", "location": {"lat": 39.1419, "lng": 43.9139}}, {"country": "Brazil", "code": "BR", "location": {"lat": -23.425, "lng": -51.9389}}, {"country": "Philippines", "code": "PH", "location": {"lat": 14.6, "lng": 120.9833}}, {"country": "China", "code": "CN", "location": {"lat": 35.4043, "lng": 107.0869}}, {"country": "Netherlands", "code": "NL", "location": {"lat": 51.8889, "lng": 5.6044}}, {"country": "United States", "code": "US", "location": {"lat": 40.3348, "lng": -78.3958}}, {"country": "Spain", "code": "ES", "location": {"lat": 43.3256, "lng": -4.0681}}, {"country": "El Salvador", "code": "SV", "location": {"lat": 13.5589, "lng": -88.43}}, {"country": "Russia", "code": "RU", "location": {"lat": 51.8464, "lng": 109.9128}}, {"country": "Japan", "code": "JP", "location": {"lat": 33.5064, "lng": 132.5447}}, {"country": "Brazil", "code": "BR", "location": {"lat": -15.4639, "lng": -39.6508}}, {"country": "Brazil", "code": "BR", "location": {"lat": -6.465, "lng": -38.18}}, {"country": "United States", "code": "US", "location": {"lat": 38.692, "lng": -120.8391}}, {"country": "Afghanistan", "code": "AF", "location": {"lat": 34.5225, "lng": 65.2517}}, {"country": "Italy", "code": "IT", "location": {"lat": 41.6425, "lng": 13.474}}, {"country": "United Kingdom", "code": "GB", "location": {"lat": 51.37, "lng": -0.792}}, {"country": "China", "code": "CN", "location": {"lat": 27.6739, "lng": 103.8739}}, {"country": "Russia", "code": "RU", "location": {"lat": 57.3833, "lng": 41.2833}}, {"country": "China", "code": "CN", "location": {"lat": 32.3849, "lng": 111.6695}}, {"country": "Brazil", "code": "BR", "location": {"lat": -29.645, "lng": -53.24}}, {"country": "Venezuela", "code": "VE", "location": {"lat": 9.9281, "lng": -69.5778}}, {"country": "Philippines", "code": "PH", "location": {"lat": 14.0333, "lng": 120.65}}, {"country": "Mexico", "code": "MX", "location": {"lat": 19, "lng": -99.4}}, {"country": "United States", "code": "US", "location": {"lat": 41.8442, "lng": -73.0055}}, {"country": "China", "code": "CN", "location": {"lat": 28.0733, "lng": 119.1277}}, {"country": "United States", "code": "US", "location": {"lat": 40.7311, "lng": -73.3251}}, {"country": "Philippines", "code": "PH", "location": {"lat": 11.2, "lng": 124.85}}, {"country": "China", "code": "CN", "location": {"lat": 24.2998, "lng": 116.1191}}, {"country": "Ukraine", "code": "UA", "location": {"lat": 46.9667, "lng": 32}}, {"country": "Congo (Kinshasa)", "code": "CD", "location": {"lat": -10.87, "lng": 26.6}}, {"country": "Brazil", "code": "BR", "location": {"lat": -19.2189, "lng": -42.0458}}, {"country": "United States", "code": "US", "location": {"lat": 46.8673, "lng": -96.7461}}, {"country": "Japan", "code": "JP", "location": {"lat": 32.8333, "lng": 129.85}}, {"country": "Thailand", "code": "TH", "location": {"lat": 15.898, "lng": 100.311}}, {"country": "Netherlands", "code": "NL", "location": {"lat": 52.2506, "lng": 6.9119}}, {"country": "Germany", "code": "DE", "location": {"lat": 50.0688, "lng": 8.5301}}, {"country": "China", "code": "CN", "location": {"lat": 42.0172, "lng": 86.3027}}, {"country": "Brazil", "code": "BR", "location": {"lat": -10.5778, "lng": -37.3428}}, {"country": "Russia", "code": "RU", "location": {"lat": 48.7833, "lng": 132.9333}}, {"country": "Spain", "code": "ES", "location": {"lat": 41.5542, "lng": 2.2886}}, {"country": "Russia", "code": "RU", "location": {"lat": 44.7167, "lng": 37.7667}}, {"country": "Germany", "code": "DE", "location": {"lat": 53.55, "lng": 10}}, {"country": "Philippines", "code": "PH", "location": {"lat": 16.4167, "lng": 120.9167}}, {"country": "Ukraine", "code": "UA", "location": {"lat": 45.2, "lng": 33.3583}}, {"country": "Finland", "code": "FI", "location": {"lat": 61.3653, "lng": 22.0042}}, {"country": "United States", "code": "US", "location": {"lat": 39.1941, "lng": -76.7427}}, {"country": "Uganda", "code": "UG", "location": {"lat": 1.145, "lng": 33.7094}}, {"country": "United States", "code": "US", "location": {"lat": 34.5983, "lng": -112.3176}}, {"country": "Ukraine", "code": "UA", "location": {"lat": 51.05, "lng": 31.9}}, {"country": "Nigeria", "code": "NG", "location": {"lat": 11.75, "lng": 11.9667}}, {"country": "United States", "code": "US", "location": {"lat": 37.2254, "lng": -80.0073}}, {"country": "Netherlands", "code": "NL", "location": {"lat": 52.1897, "lng": 4.4408}}, {"country": "Italy", "code": "IT", "location": {"lat": 40.9667, "lng": 16.0833}}, {"country": "Uzbekistan", "code": "UZ", "location": {"lat": 39.7094, "lng": 66.6614}}, {"country": "China", "code": "CN", "location": {"lat": 35.5707, "lng": 100.7798}}, {"country": "United States", "code": "US", "location": {"lat": 39.0871, "lng": -84.6178}}, {"country": "United States", "code": "US", "location": {"lat": 42.3396, "lng": -88.2038}}, {"country": "United States", "code": "US", "location": {"lat": 41.8445, "lng": -87.7593}}, {"country": "United States", "code": "US", "location": {"lat": 36.2082, "lng": -119.0897}}, {"country": "Philippines", "code": "PH", "location": {"lat": 7.5667, "lng": 124.9833}}, {"country": "Italy", "code": "IT", "location": {"lat": 46.4, "lng": 13.0167}}, {"country": "Bulgaria", "code": "BG", "location": {"lat": 42.7017, "lng": 25.8975}}, {"country": "United States", "code": "US", "location": {"lat": 33.9025, "lng": -118.0093}}, {"country": "Italy", "code": "IT", "location": {"lat": 45.7333, "lng": 8.9}}, {"country": "United Kingdom", "code": "GB", "location": {"lat": 55.422, "lng": -2.787}}, {"country": "China", "code": "CN", "location": {"lat": 21.6645, "lng": 110.8911}}, {"country": "United States", "code": "US", "location": {"lat": 40.919, "lng": -74.639}}, {"country": "South Sudan", "code": "SS", "location": {"lat": 4.85, "lng": 31.6}}, {"country": "Mexico", "code": "MX", "location": {"lat": 15.4333, "lng": -92.1167}}, {"country": "Congo (Kinshasa)", "code": "CD", "location": {"lat": -5.3495, "lng": 21.41}}, {"country": "United States", "code": "US", "location": {"lat": 45.6797, "lng": -122.6553}}, {"country": "United States", "code": "US", "location": {"lat": 43.7961, "lng": -123.0573}}, {"country": "Congo (Kinshasa)", "code": "CD", "location": {"lat": -6.1209, "lng": 23.5967}}, {"country": "Mexico", "code": "MX", "location": {"lat": 20.2944, "lng": -102.7097}}, {"country": "France", "code": "FR", "location": {"lat": 48.9236, "lng": 2.2522}}, {"country": "Brazil", "code": "BR", "location": {"lat": -21.3758, "lng": -46.5258}}, {"country": "Switzerland", "code": "CH", "location": {"lat": 47.3528, "lng": 8.34}}, {"country": "United States", "code": "US", "location": {"lat": 40.2522, "lng": -79.731}}, {"country": "United States", "code": "US", "location": {"lat": 40.8035, "lng": -73.337}}, {"country": "Canada", "code": "CA", "location": {"lat": 45.57, "lng": -73.9}}, {"country": "France", "code": "FR", "location": {"lat": 50.7467, "lng": 3.1581}}, {"country": "Brazil", "code": "BR", "location": {"lat": -20.8489, "lng": -41.1128}}, {"country": "Germany", "code": "DE", "location": {"lat": 48.2778, "lng": 8.0869}}, {"country": "Netherlands", "code": "NL", "location": {"lat": 50.95, "lng": 5.9667}}, {"country": "Spain", "code": "ES", "location": {"lat": 42.1519, "lng": -7.9575}}, {"country": "Uganda", "code": "UG", "location": {"lat": -0.8794, "lng": 30.2642}}]