[{"country":"United States","location":{"lat":42.0857,"lng":-88.4362}},{"country":"Germany","location":{"lat":48.6958,"lng":9.3175}},{"country":"France","location":{"lat":43.3903,"lng":-1.6597}},{"country":"United States","location":{"lat":33.823,"lng":-78.7089}},{"country":"Ukraine","location":{"lat":48.5953,"lng":34.4207}},{"country":"Ecuador","location":{"lat":-1.0544,"lng":-80.4544}},{"country":"Germany","location":{"lat":50.1986,"lng":6.8319}},{"country":"United States","location":{"lat":39.9297,"lng":-83.7957}},{"country":"Philippines","location":{"lat":7.9,"lng":123.85}},{"country":"Italy","location":{"lat":38.15,"lng":16.1667}},{"country":"Turkey","location":{"lat":39.7464,"lng":39.4914}},{"country":"Belarus","location":{"lat":53.0833,"lng":25.3167}},{"country":"Australia","location":{"lat":-30.9,"lng":135.3}},{"country":"Germany","location":{"lat":50.7697,"lng":7.4517}},{"country":"Morocco","location":{"lat":33.5667,"lng":-6.8936}},{"country":"United Kingdom","location":{"lat":53.9108,"lng":-0.1676}},{"country":"Hungary","location":{"lat":47.5125,"lng":20.1417}},{"country":"United Kingdom","location":{"lat":51.307,"lng":1.043}},{"country":"Italy","location":{"lat":45.0809,"lng":11.794}},{"country":"United Kingdom","location":{"lat":53.4636,"lng":-1.3439}},{"country":"Ethiopia","location":{"lat":14.2804,"lng":39.47}},{"country":"Uruguay","location":{"lat":-34.7542,"lng":-56.0042}},{"country":"United States","location":{"lat":43.3171,"lng":-76.4162}},{"country":"Morocco","location":{"lat":34.4936,"lng":-5.7108}},{"country":"United States","location":{"lat":47.3091,"lng":-122.3358}},{"country":"Brazil","location":{"lat":-20.6778,"lng":-43.61}},{"country":"Philippines","location":{"lat":7.0083,"lng":125.0894}},{"country":"France","location":{"lat":47.9325,"lng":-3.6969}},{"country":"Malta","location":{"lat":35.8992,"lng":14.4981}},{"country":"China","location":{"lat":26.8239,"lng":105.695}},{"country":"Hungary","location":{"lat":46.8167,"lng":19.9833}},{"country":"Latvia","location":{"lat":56.8614,"lng":24.35}},{"country":"Hungary","location":{"lat":47.1608,"lng":18.9456}},{"country":"Brazil","location":{"lat":-11.7254,"lng":-61.7778}},{"country":"France","location":{"lat":50.6908,"lng":2.9092}},{"country":"Brazil","location":{"lat":-17.3739,"lng":-40.2208}},{"country":"Mexico","location":{"lat":24.726,"lng":-102.984}},{"country":"France","location":{"lat":48.7775,"lng":2.0025}},{"country":"Morocco","location":{"lat":33.8136,"lng":-4.5169}},{"country":"Japan","location":{"lat":35.3333,"lng":136.8667}},{"country":"United Kingdom","location":{"lat":51.5347,"lng":0.0077}},{"country":"Slovenia","location":{"lat":46.3444,"lng":14.1744}},{"country":"United States","location":{"lat":38.2048,"lng":-85.5701}},{"country":"Somalia","location":{"lat":3.7666,"lng":47.3}},{"country":"United States","location":{"lat":35.206,"lng":-114.2327}},{"country":"France","location":{"lat":45.6386,"lng":4.3919}},{"country":"Myanmar","location":{"lat":19.3783,"lng":95.2279}},{"country":"Germany","location":{"lat":49.0306,"lng":10.9719}},{"country":"Russia","location":{"lat":57.5504,"lng":157.2333}},{"country":"United States","location":{"lat":38.9621,"lng":-84.386}},{"country":"Morocco","location":{"lat":30.7047,"lng":-8.8819}},{"country":"Venezuela","location":{"lat":10.7978,"lng":-68.3175}},{"country":"United States","location":{"lat":35.5849,"lng":-80.8265}},{"country":"United States","location":{"lat":42.3073,"lng":-75.2772}},{"country":"Malaysia","location":{"lat":1.4556,"lng":103.7611}},{"country":"France","location":{"lat":46.7211,"lng":-1.9456}},{"country":"Russia","location":{"lat":56.1167,"lng":47.5}},{"country":"India","location":{"lat":18.8,"lng":79.45}},{"country":"United States","location":{"lat":29.9157,"lng":-91.6758}},{"country":"Argentina","location":{"lat":-30.7833,"lng":-60.5833}},{"country":"Mexico","location":{"lat":19.5367,"lng":-99.1947}},{"country":"Czechia","location":{"lat":49.758,"lng":16.6643}},{"country":"Czechia","location":{"lat":49.0816,"lng":15.4373}},{"country":"Brazil","location":{"lat":-1.3608,"lng":-48.245}},{"country":"Morocco","location":{"lat":32.5681,"lng":-6.0308}},{"country":"Germany","location":{"lat":47.5833,"lng":10.55}},{"country":"Bulgaria","location":{"lat":42.6689,"lng":23.6025}},{"country":"United States","location":{"lat":39.6567,"lng":-119.6695}},{"country":"South Sudan","location":{"lat":9.25,"lng":29.8}},{"country":"Finland","location":{"lat":60.9804,"lng":25.655}},{"country":"Italy","location":{"lat":45.7061,"lng":12.4913}},{"country":"Netherlands","location":{"lat":52.3758,"lng":5.2256}},{"country":"United Kingdom","location":{"lat":52.3057,"lng":-0.5844}},{"country":"Italy","location":{"lat":37.2833,"lng":14.0833}},{"country":"Iran","location":{"lat":32.5567,"lng":51.3725}},{"country":"United States","location":{"lat":41.5271,"lng":-73.1228}},{"country":"United Kingdom","location":{"lat":52.5757,"lng":1.7235}},{"country":"Turkey","location":{"lat":36.7108,"lng":38.9478}},{"country":"Romania","location":{"lat":47.95,"lng":26.06}},{"country":"United States","location":{"lat":40.517,"lng":-107.5555}},{"country":"United States","location":{"lat":40.4442,"lng":-79.8733}},{"country":"Turkey","location":{"lat":37,"lng":35.325}},{"country":"Italy","location":{"lat":44.4333,"lng":10.4}},{"country":"United Kingdom","location":{"lat":51.293,"lng":-2.448}},{"country":"Greece","location":{"lat":40.935,"lng":24.415}},{"country":"Turkey","location":{"lat":38.7998,"lng":26.972}},{"country":"United Kingdom","location":{"lat":51.4668,"lng":-0.375}},{"country":"Sierra Leone","location":{"lat":7.8833,"lng":-11.1833}},{"country":"Brazil","location":{"lat":-16.6489,"lng":-49.4889}},{"country":"Canada","location":{"lat":49.4433,"lng":-96.8492}},{"country":"Guinea-Bissau","location":{"lat":11.8869,"lng":-15.8556}},{"country":"France","location":{"lat":48.4336,"lng":-4.4008}},{"country":"Brazil","location":{"lat":-26.9228,"lng":-49.3658}},{"country":"Philippines","location":{"lat":10.1614,"lng":125.1303}},{"country":"Senegal","location":{"lat":14.3167,"lng":-16.4167}},{"country":"Colombia","location":{"lat":8.7914,"lng":-74.1636}},{"country":"Brazil","location":{"lat":-14.2228,"lng":-42.7808}},{"country":"Korea, South","location":{"lat":37.4772,"lng":126.8664}},{"country":"New Zealand","location":{"lat":-37.1383,"lng":175.5375}},{"country":"Philippines","location":{"lat":16.5333,"lng":120.3333}}]