[{"country": "Canada", "code": "CA", "location": {"lat": 45.5926, "lng": -62.6455}}, {"country": "United States", "code": "US", "location": {"lat": 37.9477, "lng": -122.339}}, {"country": "Russia", "code": "RU", "location": {"lat": 52.9333, "lng": 158.4}}, {"country": "Canada", "code": "CA", "location": {"lat": 46.6167, "lng": -71.5167}}, {"country": "Russia", "code": "RU", "location": {"lat": 54.2333, "lng": 49.5833}}, {"country": "Australia", "code": "AU", "location": {"lat": -33.7164, "lng": 150.3772}}, {"country": "Brazil", "code": "BR", "location": {"lat": -9.1678, "lng": -36.2219}}, {"country": "China", "code": "CN", "location": {"lat": 23.3735, "lng": 116.6941}}, {"country": "Brazil", "code": "BR", "location": {"lat": -14.0989, "lng": -50.3269}}, {"country": "Russia", "code": "RU", "location": {"lat": 52.85, "lng": 32.6833}}, {"country": "United States", "code": "US", "location": {"lat": 35.4039, "lng": -94.5969}}, {"country": "Russia", "code": "RU", "location": {"lat": 56.3089, "lng": 38.7014}}, {"country": "Brazil", "code": "BR", "location": {"lat": -29.79, "lng": -50.435}}, {"country": "United States", "code": "US", "location": {"lat": 40.1358, "lng": -75.5201}}, {"country": "China", "code": "CN", "location": {"lat": 42.6229, "lng": 126.2614}}, {"country": "Colombia", "code": "CO", "location": {"lat": 6.3156, "lng": -76.1342}}, {"country": "Italy", "code": "IT", "location": {"lat": 37.4058, "lng": 13.7011}}, {"country": "Spain", "code": "ES", "location": {"lat": 43.6, "lng": -8.1331}}, {"country": "Poland", "code": "PL", "location": {"lat": 50.2, "lng": 17.8333}}, {"country": "Netherlands", "code": "NL", "location": {"lat": 53.0036, "lng": 6.0664}}, {"country": "China", "code": "CN", "location": {"lat": 23.3568, "lng": 115.5167}}, {"country": "United Kingdom", "code": "GB", "location": {"lat": 55.9046, "lng": -4.225}}, {"country": "Germany", "code": "DE", "location": {"lat": 50.9336, "lng": 12.7058}}, {"country": "Philippines", "code": "PH", "location": {"lat": 11.1429, "lng": 122.0417}}, {"country": "United States", "code": "US", "location": {"lat": 40.7752, "lng": -80.7628}}, {"country": "Latvia", "code": "LV", "location": {"lat": 57.0458, "lng": 24.4186}}, {"country": "Brazil", "code": "BR", "location": {"lat": -22.8378, "lng": -51.9728}}, {"country": "United States", "code": "US", "location": {"lat": 28.7893, "lng": -81.276}}, {"country": "United States", "code": "US", "location": {"lat": 42.1984, "lng": -70.9466}}, {"country": "Brazil", "code": "BR", "location": {"lat": -10.4478, "lng": -62.1342}}, {"country": "Romania", "code": "RO", "location": {"lat": 47.8667, "lng": 23.1333}}, {"country": "Italy", "code": "IT", "location": {"lat": 43.6854, "lng": 11.2544}}, {"country": "Czechia", "code": "CZ", "location": {"lat": 50.2335, "lng": 14.4109}}, {"country": "Latvia", "code": "LV", "location": {"lat": 56.9408, "lng": 24.2861}}, {"country": "United States", "code": "US", "location": {"lat": 40.2618, "lng": -81.848}}, {"country": "Brazil", "code": "BR", "location": {"lat": -21.0528, "lng": -49.6878}}, {"country": "Brazil", "code": "BR", "location": {"lat": -5.5031, "lng": -45.2369}}, {"country": "China", "code": "CN", "location": {"lat": 23.0636, "lng": 115.5467}}, {"country": "Austria", "code": "AT", "location": {"lat": 48.1167, "lng": 16.2667}}, {"country": "United States", "code": "US", "location": {"lat": 39.9562, "lng": -74.6}}, {"country": "Germany", "code": "DE", "location": {"lat": 48.2603, "lng": 11.4342}}, {"country": "Italy", "code": "IT", "location": {"lat": 45.8, "lng": 8.8833}}, {"country": "Germany", "code": "DE", "location": {"lat": 50.2, "lng": 9.9667}}, {"country": "United States", "code": "US", "location": {"lat": 37.9905, "lng": -122.5222}}, {"country": "United States", "code": "US", "location": {"lat": 32.9272, "lng": -96.8804}}, {"country": "United States", "code": "US", "location": {"lat": 37.3168, "lng": -122.0465}}, {"country": "India", "code": "IN", "location": {"lat": 30.3786, "lng": 76.7725}}, {"country": "Turkey", "code": "TR", "location": {"lat": 41.6781, "lng": 26.5594}}, {"country": "Romania", "code": "RO", "location": {"lat": 45.1167, "lng": 24.6667}}, {"country": "Israel", "code": "IL", "location": {"lat": 32.0231, "lng": 34.7503}}, {"country": "United States", "code": "US", "location": {"lat": 35.2335, "lng": -97.3471}}, {"country": "Germany", "code": "DE", "location": {"lat": 50.1, "lng": 11.3792}}, {"country": "Mali", "code": "ML", "location": {"lat": 16.9004, "lng": -0.35}}, {"country": "United States", "code": "US", "location": {"lat": 36.1342, "lng": -96.1284}}, {"country": "United Kingdom", "code": "GB", "location": {"lat": 56.15, "lng": -3.3333}}, {"country": "Tunisia", "code": "TN", "location": {"lat": 33.5, "lng": 11.1167}}, {"country": "China", "code": "CN", "location": {"lat": 35.1379, "lng": 110.764}}, {"country": "Germany", "code": "DE", "location": {"lat": 51.3833, "lng": 7.7667}}, {"country": "United States", "code": "US", "location": {"lat": 37.5904, "lng": -84.2898}}, {"country": "Spain", "code": "ES", "location": {"lat": 43.4125, "lng": -8.1703}}, {"country": "Slovakia", "code": "SK", "location": {"lat": 48.7714, "lng": 18.6242}}, {"country": "United States", "code": "US", "location": {"lat": 33.8073, "lng": -84.2889}}, {"country": "United States", "code": "US", "location": {"lat": 40.7469, "lng": -73.6392}}, {"country": "Germany", "code": "DE", "location": {"lat": 48.7992, "lng": 9.48}}, {"country": "Latvia", "code": "LV", "location": {"lat": 56.7175, "lng": 24.8106}}, {"country": "Germany", "code": "DE", "location": {"lat": 50.7592, "lng": 7.005}}, {"country": "Egypt", "code": "EG", "location": {"lat": 31.1, "lng": 30.95}}, {"country": "San Marino", "code": "SM", "location": {"lat": 43.9408, "lng": 12.4475}}, {"country": "Russia", "code": "RU", "location": {"lat": 64.5666, "lng": 143.2}}, {"country": "Thailand", "code": "TH", "location": {"lat": 15.9972, "lng": 101.0652}}, {"country": "Poland", "code": "PL", "location": {"lat": 49.75, "lng": 18.6333}}, {"country": "United States", "code": "US", "location": {"lat": 38.141, "lng": -90.5609}}, {"country": "Brazil", "code": "BR", "location": {"lat": -3.7178, "lng": -53.7369}}, {"country": "Romania", "code": "RO", "location": {"lat": 46.075, "lng": 25.6}}, {"country": "United States", "code": "US", "location": {"lat": 34.8232, "lng": -102.4001}}, {"country": "United States", "code": "US", "location": {"lat": 42.9351, "lng": -85.3457}}, {"country": "United States", "code": "US", "location": {"lat": 41.7995, "lng": -89.6956}}, {"country": "United States", "code": "US", "location": {"lat": 27.2213, "lng": -81.8587}}, {"country": "Russia", "code": "RU", "location": {"lat": 56.5833, "lng": 104.1167}}, {"country": "Mexico", "code": "MX", "location": {"lat": 20.5206, "lng": -99.8958}}, {"country": "Tanzania", "code": "TZ", "location": {"lat": -10.2736, "lng": 40.1828}}, {"country": "Belgium", "code": "BE", "location": {"lat": 51.1919, "lng": 4.7386}}, {"country": "Germany", "code": "DE", "location": {"lat": 47.7356, "lng": 8.7767}}, {"country": "Germany", "code": "DE", "location": {"lat": 49.9242, "lng": 8.4092}}, {"country": "Germany", "code": "DE", "location": {"lat": 51.1, "lng": 9.3333}}, {"country": "Thailand", "code": "TH", "location": {"lat": 18.9163, "lng": 98.9605}}, {"country": "France", "code": "FR", "location": {"lat": 43.5156, "lng": 1.4981}}, {"country": "United Kingdom", "code": "GB", "location": {"lat": 52.5727, "lng": -1.2023}}, {"country": "Brazil", "code": "BR", "location": {"lat": -12.1578, "lng": -39.7369}}, {"country": "Pakistan", "code": "PK", "location": {"lat": 34.7717, "lng": 72.36}}, {"country": "Italy", "code": "IT", "location": {"lat": 43.95, "lng": 10.1833}}, {"country": "United Kingdom", "code": "GB", "location": {"lat": 51.3033, "lng": 0.4796}}, {"country": "Kazakhstan", "code": "KZ", "location": {"lat": 43.5953, "lng": 73.7448}}, {"country": "Timor-Leste", "code": "TL", "location": {"lat": -9.3129, "lng": 125.2565}}, {"country": "Germany", "code": "DE", "location": {"lat": 50.8167, "lng": 6.3497}}, {"country": "Romania", "code": "RO", "location": {"lat": 47.8425, "lng": 25.9192}}, {"country": "Brazil", "code": "BR", "location": {"lat": -21.1336, "lng": -51.1017}}, {"country": "Germany", "code": "DE", "location": {"lat": 52.9999, "lng": 9.1732}}, {"country": "Germany", "code": "DE", "location": {"lat": 52.2394, "lng": 9.8606}}, {"country": "Brazil", "code": "BR", "location": {"lat": -6.8719, "lng": -41.475}}]