[{"country": "Germany", "code": "DE", "location": {"lat": 51.5264, "lng": 12.3425}}, {"country": "Philippines", "code": "PH", "location": {"lat": 13.5667, "lng": 123.15}}, {"country": "France", "code": "FR", "location": {"lat": 48.9469, "lng": 2.1456}}, {"country": "Slovakia", "code": "SK", "location": {"lat": 47.8761, "lng": 18.1972}}, {"country": "Brazil", "code": "BR", "location": {"lat": -9.8058, "lng": -37.685}}, {"country": "Morocco", "code": "MA", "location": {"lat": 31.21, "lng": -8.25}}, {"country": "Philippines", "code": "PH", "location": {"lat": 8.9855, "lng": 124.7937}}, {"country": "Brazil", "code": "BR", "location": {"lat": -18.7628, "lng": -50.9419}}, {"country": "Argentina", "code": "AR", "location": {"lat": -34.7, "lng": -58.2833}}, {"country": "Brazil", "code": "BR", "location": {"lat": -19.23, "lng": -42.3278}}, {"country": "United States", "code": "US", "location": {"lat": 44.735, "lng": -68.8896}}, {"country": "Egypt", "code": "EG", "location": {"lat": 30.547, "lng": 31.2673}}, {"country": "Germany", "code": "DE", "location": {"lat": 49.9297, "lng": 8.3133}}, {"country": "United States", "code": "US", "location": {"lat": 38.7499, "lng": -76.9063}}, {"country": "Japan", "code": "JP", "location": {"lat": 43.2447, "lng": 143.5542}}, {"country": "Ukraine", "code": "UA", "location": {"lat": 48.7664, "lng": 37.6314}}, {"country": "Brazil", "code": "BR", "location": {"lat": -29.4478, "lng": -51.8058}}, {"country": "Mozambique", "code": "MZ", "location": {"lat": -24.6867, "lng": 33.5306}}, {"country": "United States", "code": "US", "location": {"lat": 41.3483, "lng": -86.3187}}, {"country": "Iran", "code": "IR", "location": {"lat": 37.4667, "lng": 49.4667}}, {"country": "Mexico", "code": "MX", "location": {"lat": 22.4004, "lng": -105.46}}, {"country": "Spain", "code": "ES", "location": {"lat": 39.8983, "lng": -5.5403}}, {"country": "Thailand", "code": "TH", "location": {"lat": 17.4333, "lng": 103.4051}}, {"country": "Indonesia", "code": "ID", "location": {"lat": -2.21, "lng": 113.92}}, {"country": "Moldova", "code": "MD", "location": {"lat": 47.0931, "lng": 28.6583}}, {"country": "United States", "code": "US", "location": {"lat": 42.4456, "lng": -71.2307}}, {"country": "Moldova", "code": "MD", "location": {"lat": 47.1536, "lng": 29.2964}}, {"country": "United States", "code": "US", "location": {"lat": 33.2872, "lng": -96.9622}}, {"country": "China", "code": "CN", "location": {"lat": 25.1945, "lng": 101.2759}}, {"country": "Germany", "code": "DE", "location": {"lat": 49.8667, "lng": 11.8833}}, {"country": "Germany", "code": "DE", "location": {"lat": 50.4925, "lng": 6.6297}}, {"country": "Colombia", "code": "CO", "location": {"lat": 10.3247, "lng": -74.9589}}, {"country": "France", "code": "FR", "location": {"lat": 48.7422, "lng": 2.2261}}, {"country": "United Kingdom", "code": "GB", "location": {"lat": 53.309, "lng": -3.738}}, {"country": "United Kingdom", "code": "GB", "location": {"lat": 53.748, "lng": -2.482}}, {"country": "France", "code": "FR", "location": {"lat": 43.9544, "lng": 4.7667}}, {"country": "Germany", "code": "DE", "location": {"lat": 53.8111, "lng": 9.6183}}, {"country": "China", "code": "CN", "location": {"lat": 36.8624, "lng": 105.9915}}, {"country": "Italy", "code": "IT", "location": {"lat": 41.0667, "lng": 14.2833}}, {"country": "United States", "code": "US", "location": {"lat": 38.1133, "lng": -122.2358}}, {"country": "Tanzania", "code": "TZ", "location": {"lat": -7.3996, "lng": 36.98}}, {"country": "United Kingdom", "code": "GB", "location": {"lat": 53.572, "lng": -2.69}}, {"country": "C\u00f4te D\u2019Ivoire", "code": "CI", "location": {"lat": 5.9333, "lng": -4.2167}}, {"country": "Germany", "code": "DE", "location": {"lat": 49.5394, "lng": 6.89}}, {"country": "Brazil", "code": "BR", "location": {"lat": -7.0478, "lng": -35.9308}}, {"country": "Ukraine", "code": "UA", "location": {"lat": 48.95, "lng": 38.4833}}, {"country": "Morocco", "code": "MA", "location": {"lat": 34.2, "lng": -4.2833}}, {"country": "United States", "code": "US", "location": {"lat": 33.2284, "lng": -117.3791}}, {"country": "Brazil", "code": "BR", "location": {"lat": -19.0669, "lng": -51.5439}}, {"country": "Italy", "code": "IT", "location": {"lat": 45.4667, "lng": 8.9167}}, {"country": "United States", "code": "US", "location": {"lat": 47.5086, "lng": -122.348}}, {"country": "United Kingdom", "code": "GB", "location": {"lat": 53.515, "lng": -1.133}}, {"country": "Russia", "code": "RU", "location": {"lat": 56.5, "lng": 66.55}}, {"country": "United States", "code": "US", "location": {"lat": 42.9234, "lng": -89.2215}}, {"country": "Philippines", "code": "PH", "location": {"lat": 6.55, "lng": 125.4667}}, {"country": "Ukraine", "code": "UA", "location": {"lat": 48.35, "lng": 39.7167}}, {"country": "United States", "code": "US", "location": {"lat": 39.806, "lng": -75.9895}}, {"country": "Libya", "code": "LY", "location": {"lat": 32.1669, "lng": 13.0167}}, {"country": "Germany", "code": "DE", "location": {"lat": 50.3, "lng": 8.2667}}, {"country": "United Kingdom", "code": "GB", "location": {"lat": 51.61, "lng": -3.65}}, {"country": "Italy", "code": "IT", "location": {"lat": 36.7914, "lng": 14.7025}}, {"country": "Spain", "code": "ES", "location": {"lat": 28.35, "lng": -14.1}}, {"country": "Russia", "code": "RU", "location": {"lat": 51.2981, "lng": 37.835}}, {"country": "Brazil", "code": "BR", "location": {"lat": -8.1628, "lng": -40.6158}}, {"country": "Germany", "code": "DE", "location": {"lat": 48.1167, "lng": 12.5833}}, {"country": "Italy", "code": "IT", "location": {"lat": 42.0028, "lng": 14.9947}}, {"country": "Ukraine", "code": "UA", "location": {"lat": 48.35, "lng": 31.1667}}, {"country": "Germany", "code": "DE", "location": {"lat": 50.6667, "lng": 9.7667}}, {"country": "Egypt", "code": "EG", "location": {"lat": 30.8267, "lng": 31.2226}}, {"country": "United States", "code": "US", "location": {"lat": 41.2396, "lng": -81.3456}}, {"country": "Russia", "code": "RU", "location": {"lat": 60.6167, "lng": 47.2833}}, {"country": "Belgium", "code": "BE", "location": {"lat": 50.7361, "lng": 4.2372}}, {"country": "Philippines", "code": "PH", "location": {"lat": 15.9, "lng": 120.8}}, {"country": "Italy", "code": "IT", "location": {"lat": 44.9, "lng": 9.6}}, {"country": "Germany", "code": "DE", "location": {"lat": 50.6872, "lng": 10.9142}}, {"country": "France", "code": "FR", "location": {"lat": 43.3844, "lng": -1.3047}}, {"country": "Mexico", "code": "MX", "location": {"lat": 28.0333, "lng": -105.2833}}, {"country": "France", "code": "FR", "location": {"lat": 46.1075, "lng": 5.8258}}, {"country": "United States", "code": "US", "location": {"lat": 41.0769, "lng": -111.9621}}, {"country": "United States", "code": "US", "location": {"lat": 37.0335, "lng": -88.6859}}, {"country": "United States", "code": "US", "location": {"lat": 39.9784, "lng": -74.9413}}, {"country": "United States", "code": "US", "location": {"lat": 38.8093, "lng": -121.1955}}, {"country": "United States", "code": "US", "location": {"lat": 26.3197, "lng": -98.1596}}, {"country": "Georgia", "code": "GE", "location": {"lat": 42.0845, "lng": 44.6961}}, {"country": "Philippines", "code": "PH", "location": {"lat": 13.9667, "lng": 121.0833}}, {"country": "Italy", "code": "IT", "location": {"lat": 42.4, "lng": 14.05}}, {"country": "United States", "code": "US", "location": {"lat": 34.2565, "lng": -80.6087}}, {"country": "Spain", "code": "ES", "location": {"lat": 37.4333, "lng": -4.1833}}, {"country": "Italy", "code": "IT", "location": {"lat": 46.05, "lng": 13.2}}, {"country": "China", "code": "CN", "location": {"lat": 35.7056, "lng": 109.5855}}, {"country": "Hungary", "code": "HU", "location": {"lat": 47.3475, "lng": 19.4489}}, {"country": "Venezuela", "code": "VE", "location": {"lat": 10.1889, "lng": -64.6951}}, {"country": "Turkmenistan", "code": "TM", "location": {"lat": 37.95, "lng": 58.3833}}, {"country": "Russia", "code": "RU", "location": {"lat": 45.0333, "lng": 38.9833}}, {"country": "Germany", "code": "DE", "location": {"lat": 51.6708, "lng": 8.6047}}, {"country": "Ukraine", "code": "UA", "location": {"lat": 45.6855, "lng": 28.6134}}, {"country": "Philippines", "code": "PH", "location": {"lat": 16.3667, "lng": 120.6833}}, {"country": "United States", "code": "US", "location": {"lat": 39.3167, "lng": -74.6066}}, {"country": "United States", "code": "US", "location": {"lat": 42.6373, "lng": -70.9425}}, {"country": "United States", "code": "US", "location": {"lat": 43.2294, "lng": -73.56}}]