[{"country":"India","location":{"lat":26.2918,"lng":73.0168}},{"country":"Brazil","location":{"lat":-21.6758,"lng":-50.3267}},{"country":"Slovenia","location":{"lat":46.075,"lng":15.5603}},{"country":"France","location":{"lat":46.3333,"lng":6.0578}},{"country":"United States","location":{"lat":64.9295,"lng":-147.3955}},{"country":"Ukraine","location":{"lat":48.0556,"lng":37.9611}},{"country":"France","location":{"lat":50.6901,"lng":3.1817}},{"country":"Brazil","location":{"lat":-18.0439,"lng":-41.11}},{"country":"France","location":{"lat":43.5263,"lng":5.4454}},{"country":"Slovenia","location":{"lat":45.6847,"lng":13.9703}},{"country":"France","location":{"lat":49.49,"lng":0.1}},{"country":"Philippines","location":{"lat":14.9667,"lng":120.7167}},{"country":"Argentina","location":{"lat":-35.4167,"lng":-60.1667}},{"country":"Germany","location":{"lat":52.2833,"lng":11.4167}},{"country":"France","location":{"lat":48.8239,"lng":2.2117}},{"country":"Faroe Islands","location":{"lat":62.2079,"lng":-6.9997}},{"country":"Italy","location":{"lat":44.6475,"lng":11.5353}},{"country":"Bulgaria","location":{"lat":43.3481,"lng":26.2275}},{"country":"United States","location":{"lat":42.2466,"lng":-71.1777}},{"country":"United States","location":{"lat":38.44,"lng":-90.9927}},{"country":"Morocco","location":{"lat":35.1536,"lng":-2.9861}},{"country":"Mexico","location":{"lat":32.5667,"lng":-116.6331}},{"country":"United States","location":{"lat":41.0212,"lng":-72.1584}},{"country":"Romania","location":{"lat":44.3434,"lng":25.9421}},{"country":"Colombia","location":{"lat":5.9978,"lng":-72.6922}},{"country":"United States","location":{"lat":28.2669,"lng":-82.6257}},{"country":"Mexico","location":{"lat":20.2167,"lng":-104.167}},{"country":"Philippines","location":{"lat":10.8231,"lng":122.5344}},{"country":"Germany","location":{"lat":51.8036,"lng":12.4064}},{"country":"Austria","location":{"lat":48.3456,"lng":14.0503}},{"country":"Mexico","location":{"lat":19.1264,"lng":-98.8028}},{"country":"Italy","location":{"lat":42.1,"lng":12.1833}},{"country":"Niger","location":{"lat":13.05,"lng":3.2}},{"country":"Romania","location":{"lat":46.8403,"lng":27.4417}},{"country":"United Kingdom","location":{"lat":54.5406,"lng":-1.2124}},{"country":"Portugal","location":{"lat":38.7704,"lng":-9.3081}},{"country":"Japan","location":{"lat":36.0269,"lng":139.53}},{"country":"United States","location":{"lat":39.6967,"lng":-75.4475}},{"country":"Romania","location":{"lat":44.6833,"lng":26.0167}},{"country":"Switzerland","location":{"lat":47.2401,"lng":8.7328}},{"country":"United States","location":{"lat":47.3374,"lng":-122.2812}},{"country":"Somalia","location":{"lat":0.0722,"lng":42.7506}},{"country":"Mexico","location":{"lat":17.9561,"lng":-102.1922}},{"country":"Iran","location":{"lat":35.3433,"lng":52.0675}},{"country":"United States","location":{"lat":39.4313,"lng":-121.5225}},{"country":"Philippines","location":{"lat":7.8833,"lng":124.3833}},{"country":"Norway","location":{"lat":70.6634,"lng":23.6821}},{"country":"Mexico","location":{"lat":20.2231,"lng":-99.8147}},{"country":"Morocco","location":{"lat":31.2167,"lng":-9.0833}},{"country":"United States","location":{"lat":40.1812,"lng":-76.1811}},{"country":"United States","location":{"lat":39.6879,"lng":-119.8364}},{"country":"Serbia","location":{"lat":43.6167,"lng":20.9}},{"country":"United States","location":{"lat":37.336,"lng":-79.5179}},{"country":"Libya","location":{"lat":32.7604,"lng":12.72}},{"country":"Brazil","location":{"lat":-7.875,"lng":-35.45}},{"country":"Libya","location":{"lat":32.9333,"lng":12.0833}},{"country":"Italy","location":{"lat":41.5,"lng":15.3333}},{"country":"Thailand","location":{"lat":7.0167,"lng":100.4667}},{"country":"Guatemala","location":{"lat":14.9322,"lng":-90.1433}},{"country":"Philippines","location":{"lat":12.1335,"lng":119.9363}},{"country":"Indonesia","location":{"lat":-7.4722,"lng":112.4336}},{"country":"Russia","location":{"lat":61,"lng":69}},{"country":"Germany","location":{"lat":53.8667,"lng":8.7}},{"country":"Spain","location":{"lat":42.5667,"lng":-8.9833}},{"country":"France","location":{"lat":42.6542,"lng":2.9517}},{"country":"Sao Tome And Principe","location":{"lat":1.6806,"lng":7.4394}},{"country":"Tunisia","location":{"lat":36.8333,"lng":10.3167}},{"country":"Iran","location":{"lat":29.5833,"lng":50.5167}},{"country":"United States","location":{"lat":42.9955,"lng":-84.176}},{"country":"United Kingdom","location":{"lat":53.099,"lng":-2.44}},{"country":"France","location":{"lat":43.6136,"lng":1.0808}},{"country":"Mexico","location":{"lat":21.5397,"lng":-105.2856}},{"country":"Italy","location":{"lat":43.1007,"lng":10.5388}},{"country":"Brazil","location":{"lat":-0.9428,"lng":-47.1158}},{"country":"Russia","location":{"lat":54.0331,"lng":58.8025}},{"country":"Italy","location":{"lat":40.3919,"lng":17.4483}},{"country":"Philippines","location":{"lat":16.8206,"lng":121.4629}},{"country":"Estonia","location":{"lat":59.4372,"lng":24.745}},{"country":"France","location":{"lat":44.9344,"lng":4.8747}},{"country":"Slovenia","location":{"lat":46.5662,"lng":16.4499}},{"country":"France","location":{"lat":48.7586,"lng":1.9622}},{"country":"Morocco","location":{"lat":34.5406,"lng":-4.7294}},{"country":"Brazil","location":{"lat":-4.1419,"lng":-40.5819}},{"country":"United States","location":{"lat":33.2421,"lng":-95.8991}},{"country":"Italy","location":{"lat":43.9452,"lng":10.2183}},{"country":"Thailand","location":{"lat":13.3515,"lng":102.1833}},{"country":"United States","location":{"lat":36.9618,"lng":-121.9715}},{"country":"Benin","location":{"lat":6.4,"lng":2.52}},{"country":"Canada","location":{"lat":45.9,"lng":-77.2833}},{"country":"India","location":{"lat":27.18,"lng":78.02}},{"country":"United States","location":{"lat":42.2893,"lng":-89.6347}},{"country":"Mozambique","location":{"lat":-25.0333,"lng":33.1}},{"country":"Philippines","location":{"lat":9.5907,"lng":123.1213}},{"country":"United States","location":{"lat":39.732,"lng":-105.1785}},{"country":"Belgium","location":{"lat":50.2355,"lng":4.2383}},{"country":"United States","location":{"lat":39.339,"lng":-94.24}},{"country":"United States","location":{"lat":40.6136,"lng":-89.4669}},{"country":"United States","location":{"lat":39.8321,"lng":-105.1511}},{"country":"Romania","location":{"lat":45.2697,"lng":28.4597}},{"country":"United Kingdom","location":{"lat":51.371,"lng":-2.138}}]