[{"country":"Spain","location":{"lat":41.4767,"lng":1.9822}},{"country":"Dominican Republic","location":{"lat":18.46,"lng":-70.74}},{"country":"Kyrgyzstan","location":{"lat":39.9333,"lng":71.3333}},{"country":"United States","location":{"lat":42.3465,"lng":-73.8624}},{"country":"Mexico","location":{"lat":19.1756,"lng":-99.4886}},{"country":"United States","location":{"lat":46.734,"lng":-117.1669}},{"country":"Switzerland","location":{"lat":47.2081,"lng":7.5375}},{"country":"Philippines","location":{"lat":16.15,"lng":120.45}},{"country":"China","location":{"lat":38.827,"lng":110.499}},{"country":"Ukraine","location":{"lat":48.5333,"lng":37.7167}},{"country":"Brazil","location":{"lat":-29.4689,"lng":-52.0878}},{"country":"United States","location":{"lat":42.4235,"lng":-83.7524}},{"country":"Spain","location":{"lat":41.3319,"lng":1.9228}},{"country":"Indonesia","location":{"lat":-6.0027,"lng":106.0112}},{"country":"Iran","location":{"lat":36.5208,"lng":46.2117}},{"country":"Germany","location":{"lat":51.6825,"lng":10.0992}},{"country":"United States","location":{"lat":41.9225,"lng":-87.8163}},{"country":"Czechia","location":{"lat":49.523,"lng":16.2615}},{"country":"Philippines","location":{"lat":8.9167,"lng":125.0167}},{"country":"United States","location":{"lat":42.2826,"lng":-87.851}},{"country":"United States","location":{"lat":35.5285,"lng":-97.6182}},{"country":"Brazil","location":{"lat":-26.9,"lng":-48.8269}},{"country":"Kazakhstan","location":{"lat":43.6905,"lng":51.1417}},{"country":"Ukraine","location":{"lat":49.1992,"lng":39.5756}},{"country":"Switzerland","location":{"lat":47.3344,"lng":7.8444}},{"country":"Brazil","location":{"lat":-18.2189,"lng":-42.4989}},{"country":"Uganda","location":{"lat":-0.0772,"lng":31.4567}},{"country":"United States","location":{"lat":41.6642,"lng":-73.0263}},{"country":"Brazil","location":{"lat":-8.1189,"lng":-38.7278}},{"country":"Germany","location":{"lat":48.8714,"lng":9.3531}},{"country":"Italy","location":{"lat":45.4583,"lng":12.008}},{"country":"Mexico","location":{"lat":21.2333,"lng":-98}},{"country":"Germany","location":{"lat":48.2903,"lng":9.1094}},{"country":"Brazil","location":{"lat":-11.66,"lng":-38.0808}},{"country":"United Kingdom","location":{"lat":51.465,"lng":0.033}},{"country":"Philippines","location":{"lat":14.5119,"lng":121.2389}},{"country":"Thailand","location":{"lat":12.9658,"lng":99.8924}},{"country":"Mexico","location":{"lat":25.8797,"lng":-97.5042}},{"country":"Japan","location":{"lat":32.7144,"lng":130.8019}},{"country":"France","location":{"lat":49.1147,"lng":6.8636}},{"country":"Germany","location":{"lat":49.7225,"lng":8.6139}},{"country":"France","location":{"lat":43.1056,"lng":6.0233}},{"country":"Norway","location":{"lat":59.7647,"lng":10.0333}},{"country":"United States","location":{"lat":40.8982,"lng":-111.9082}},{"country":"Brazil","location":{"lat":-6.73,"lng":-38.7169}},{"country":"Italy","location":{"lat":41.05,"lng":15.8}},{"country":"United Kingdom","location":{"lat":56.0339,"lng":-3.4323}},{"country":"Germany","location":{"lat":48.2353,"lng":9.6439}},{"country":"China","location":{"lat":32.9354,"lng":117.3531}},{"country":"Austria","location":{"lat":46.6867,"lng":15.2472}},{"country":"Italy","location":{"lat":40.8206,"lng":16.4233}},{"country":"Hungary","location":{"lat":47.4353,"lng":19.3986}},{"country":"Norway","location":{"lat":58.9701,"lng":5.7333}},{"country":"Turkmenistan","location":{"lat":39.4,"lng":53.1167}},{"country":"Philippines","location":{"lat":14.65,"lng":120.9667}},{"country":"Slovenia","location":{"lat":46.3833,"lng":14.0833}},{"country":"Germany","location":{"lat":53.9667,"lng":14.1667}},{"country":"Italy","location":{"lat":41.0333,"lng":14.4833}},{"country":"Australia","location":{"lat":-41.1806,"lng":146.3464}},{"country":"Italy","location":{"lat":43.95,"lng":10.1833}},{"country":"Algeria","location":{"lat":35.4489,"lng":2.9044}},{"country":"United States","location":{"lat":39.7452,"lng":-77.0892}},{"country":"Uruguay","location":{"lat":-33.5333,"lng":-58.2167}},{"country":"United Kingdom","location":{"lat":53.596,"lng":-2.843}},{"country":"Poland","location":{"lat":50.6833,"lng":21.75}},{"country":"United States","location":{"lat":26.9618,"lng":-80.1011}},{"country":"United Kingdom","location":{"lat":51.4415,"lng":0.3685}},{"country":"Brazil","location":{"lat":-21.17,"lng":-44.925}},{"country":"Azerbaijan","location":{"lat":40.9111,"lng":49.0694}},{"country":"Mexico","location":{"lat":19.6833,"lng":-101.95}},{"country":"Venezuela","location":{"lat":9.7822,"lng":-69.7931}},{"country":"Bolivia","location":{"lat":-20.4547,"lng":-63.5189}},{"country":"Italy","location":{"lat":45.8833,"lng":13.5}},{"country":"United States","location":{"lat":39.5061,"lng":-84.7434}},{"country":"South Africa","location":{"lat":-33.15,"lng":18.6667}},{"country":"Azerbaijan","location":{"lat":40.9053,"lng":45.5564}},{"country":"China","location":{"lat":24.1681,"lng":115.6669}},{"country":"United States","location":{"lat":38.8391,"lng":-77.4388}},{"country":"United States","location":{"lat":41.112,"lng":-73.8122}},{"country":"Switzerland","location":{"lat":47.3875,"lng":8.1803}},{"country":"Germany","location":{"lat":52.5055,"lng":9.4636}},{"country":"Germany","location":{"lat":51.9886,"lng":9.8269}},{"country":"Brazil","location":{"lat":-15.8025,"lng":-43.3089}},{"country":"United States","location":{"lat":40.2165,"lng":-75.419}},{"country":"United States","location":{"lat":39.9016,"lng":-74.9297}},{"country":"Brazil","location":{"lat":-8.6239,"lng":-35.5328}},{"country":"Germany","location":{"lat":52.6,"lng":12.8831}},{"country":"United Kingdom","location":{"lat":53.797,"lng":-1.663}},{"country":"Ukraine","location":{"lat":45.2,"lng":33.3583}},{"country":"Spain","location":{"lat":28.6825,"lng":-17.765}},{"country":"Colombia","location":{"lat":-3.7703,"lng":-70.3831}},{"country":"United States","location":{"lat":40.2905,"lng":-75.7477}},{"country":"Morocco","location":{"lat":32.3528,"lng":-7.3245}},{"country":"Belgium","location":{"lat":50.1286,"lng":5.3419}},{"country":"Azerbaijan","location":{"lat":40.77,"lng":47.0489}},{"country":"Brazil","location":{"lat":-8.1819,"lng":-43.7919}},{"country":"Italy","location":{"lat":45.95,"lng":12.4167}},{"country":"United States","location":{"lat":34.6988,"lng":-86.6412}},{"country":"Switzerland","location":{"lat":46.2167,"lng":6.1833}},{"country":"Germany","location":{"lat":49.2333,"lng":7}}]